{
    "7316010020001": {
        "Koperasi": "Koperasi Pegawai Negeri Srikandi SMP Negeri 1 Maiwa",
        "Nomor Badan Hukum Pendirian": "4896/BH/IV",
        "Tanggal Badan Hukum Pendirian": "13/12/1988",
        "Nomor Perubahan Anggaran Dasar (Terbaru)": "423/PAD/KWK.20/VI/1997",
        "Tanggal Perubahan Anggaran Dasar (Terbaru)": "10/06/1997",
        "Tanggal RAT Terakhir": "10/06/2021",
        "Alamat": "Jl. Jend. Sudirman No. 47 Maroangin",
        "Kelurahan / Desa": "Bangkala",
        "Kecamatan": "Maiwa",
        "Kabupaten": "Kab. Enrekang",
        "Provinsi": "Sulawesi Selatan",
        "Bentuk Koperasi": "Primer Kabupaten/Kota",
        "Jenis Koperasi": "Konsumen",
        "Kelompok Koperasi": "Kop. Pegawai Negeri (KPRI)",
        "Sektor Usaha": "Jasa Keuangan dan Asuransi",
        "Nama Ketua": "Alimus Muhammad Nur,S,Pd.M.Pd",
        "Nama Sekretaris": "Sainuddin",
        "Nama Bendahara": "Dra.Hj.hasnawati",
        "Nama Pengawas": " ",
        "Nama Manager": " ",
        "Jumlah Anggota Pria": "25",
        "Jumlah Anggota Wanita": "39",
        "Total Anggota": "64",
        "Total Manajer": "0",
        "Total Karyawan": "0",
        "Nomor Induk Koperasi (NIK)": "7316010020001",
        "Status NIK": "Sertifikat - Expired",
        "Tanggal Berlaku Sertifikat": "13/12/2019",
        "Status Grade": "A"
    },
    "7316010020002": {
        "Koperasi": "Koperasi Berkah SMU Negeri 1 Maiwa",
        "Nomor Badan Hukum Pendirian": "108/KEP-BH/PPD/2.1/IX/2004",
        "Tanggal Badan Hukum Pendirian": "06/09/2004",
        "Nomor Perubahan Anggaran Dasar (Terbaru)": "-",
        "Tanggal Perubahan Anggaran Dasar (Terbaru)": " ",
        "Tanggal RAT Terakhir": "07/03/2018",
        "Alamat": "Jl. Jeruk Manis, Maroangin",
        "Kelurahan / Desa": "Bangkala",
        "Kecamatan": "Maiwa",
        "Kabupaten": "Kab. Enrekang",
        "Provinsi": "Sulawesi Selatan",
        "Bentuk Koperasi": "Primer Kabupaten/Kota",
        "Jenis Koperasi": "Konsumen",
        "Kelompok Koperasi": "Kop. Pegawai Negeri (KPRI)",
        "Sektor Usaha": "Jasa Keuangan dan Asuransi",
        "Nama Ketua": "Drs. Agussalim",
        "Nama Sekretaris": "Sitti Suhria Rasyid",
        "Nama Bendahara": "Muh. Sadar",
        "Nama Pengawas": " ",
        "Nama Manager": " ",
        "Jumlah Anggota Pria": "14",
        "Jumlah Anggota Wanita": "17",
        "Total Anggota": "31",
        "Total Manajer": "0",
        "Total Karyawan": "4",
        "Nomor Induk Koperasi (NIK)": "7316010020002",
        "Status NIK": "Sertifikat - Expired",
        "Tanggal Berlaku Sertifikat": "06/09/2019",
        "Status Grade": "D"
    },
    "7316010020003": {
        "Koperasi": "Koperasi Wanita Sejahtera",
        "Nomor Badan Hukum Pendirian": "5477/BH/IV",
        "Tanggal Badan Hukum Pendirian": "05/10/1994",
        "Nomor Perubahan Anggaran Dasar (Terbaru)": " ",
        "Tanggal Perubahan Anggaran Dasar (Terbaru)": " ",
        "Tanggal RAT Terakhir": "23/03/2021",
        "Alamat": "Jl. Pramuka No. 8 Maroangin",
        "Kelurahan / Desa": "Bangkala",
        "Kecamatan": "Maiwa",
        "Kabupaten": "Kab. Enrekang",
        "Provinsi": "Sulawesi Selatan",
        "Bentuk Koperasi": "Primer Kabupaten/Kota",
        "Jenis Koperasi": "Konsumen",
        "Kelompok Koperasi": "Kop. Wanita",
        "Sektor Usaha": "Jasa Keuangan dan Asuransi",
        "Nama Ketua": "Hjj. husniati Hawing, S. Pd.",
        "Nama Sekretaris": "Hj. Mansuarni Saleh, S.Pd",
        "Nama Bendahara": "Fitriani Hawing, S.Pd",
        "Nama Pengawas": " ",
        "Nama Manager": " ",
        "Jumlah Anggota Pria": "12",
        "Jumlah Anggota Wanita": "187",
        "Total Anggota": "199",
        "Total Manajer": "0",
        "Total Karyawan": "0",
        "Nomor Induk Koperasi (NIK)": "7316010020003",
        "Status NIK": "Sertifikat - Expired",
        "Tanggal Berlaku Sertifikat": "05/10/2020",
        "Status Grade": "A"
    },
    "7316010020004": {
        "Koperasi": "Koperasi Simpan Pinjam Harapan Mulia Bersama",
        "Nomor Badan Hukum Pendirian": "004803/BH/M.KUKM.2/VII/2017",
        "Tanggal Badan Hukum Pendirian": "25/07/2017",
        "Nomor Perubahan Anggaran Dasar (Terbaru)": " ",
        "Tanggal Perubahan Anggaran Dasar (Terbaru)": " ",
        "Tanggal RAT Terakhir": "09/03/2021",
        "Alamat": "Maroangin",
        "Kelurahan / Desa": "Bangkala",
        "Kecamatan": "Maiwa",
        "Kabupaten": "Kab. Enrekang",
        "Provinsi": "Sulawesi Selatan",
        "Bentuk Koperasi": "Primer Kabupaten/Kota",
        "Jenis Koperasi": "Simpan Pinjam",
        "Kelompok Koperasi": "Kop. Simpan Pinjam",
        "Sektor Usaha": "Jasa Keuangan dan Asuransi",
        "Nama Ketua": "Drs. Kudding, M. Si",
        "Nama Sekretaris": "Natsir, S , Pd",
        "Nama Bendahara": "Hasmawati . S , S.Pd",
        "Nama Pengawas": " ",
        "Nama Manager": " ",
        "Jumlah Anggota Pria": "95",
        "Jumlah Anggota Wanita": "170",
        "Total Anggota": "265",
        "Total Manajer": "0",
        "Total Karyawan": "0",
        "Nomor Induk Koperasi (NIK)": "7316010020004",
        "Status NIK": "Sertifikat - Expired",
        "Tanggal Berlaku Sertifikat": "25/07/2020",
        "Status Grade": "A"
    },
    "7316010060001": {
        "Koperasi": "Koperasi Pondok Pesantren Rahmatul Asri",
        "Nomor Badan Hukum Pendirian": "45/BH/KDK.20.21/IV/1999",
        "Tanggal Badan Hukum Pendirian": "29/04/1999",
        "Nomor Perubahan Anggaran Dasar (Terbaru)": " ",
        "Tanggal Perubahan Anggaran Dasar (Terbaru)": " ",
        "Tanggal RAT Terakhir": "07/05/2018",
        "Alamat": "Jl. Poros Enrekang KM 1 Maroangin",
        "Kelurahan / Desa": "Desa Botto Mallangga",
        "Kecamatan": "Maiwa",
        "Kabupaten": "Kab. Enrekang",
        "Provinsi": "Sulawesi Selatan",
        "Bentuk Koperasi": "Primer Kabupaten/Kota",
        "Jenis Koperasi": "Konsumen",
        "Kelompok Koperasi": "Koppontren",
        "Sektor Usaha": "Jasa Keuangan dan Asuransi",
        "Nama Ketua": "Ermin Nur",
        "Nama Sekretaris": "Wahyuddin, S.kKm",
        "Nama Bendahara": "Hj. Zubaedah",
        "Nama Pengawas": " ",
        "Nama Manager": " ",
        "Jumlah Anggota Pria": "19",
        "Jumlah Anggota Wanita": "22",
        "Total Anggota": "41",
        "Total Manajer": "0",
        "Total Karyawan": "4",
        "Nomor Induk Koperasi (NIK)": "7316010060001",
        "Status NIK": "Sudah Bersertifikat",
        "Tanggal Berlaku Sertifikat": "29/04/2022",
        "Status Grade": "D"
    },
    "7316020010053": {
        "Koperasi": "Primer Koperasi Veteran Republik Indonesia Kabupaten Enrekang",
        "Nomor Badan Hukum Pendirian": "4409/BH/KDK",
        "Tanggal Badan Hukum Pendirian": "16/01/1985",
        "Nomor Perubahan Anggaran Dasar (Terbaru)": "91/PAD/KWK.20/X/1997",
        "Tanggal Perubahan Anggaran Dasar (Terbaru)": "06/10/1997",
        "Tanggal RAT Terakhir": "20/05/2020",
        "Alamat": "Enrekang Kelurahan Juppandang",
        "Kelurahan / Desa": "Kelurahan Juppandang",
        "Kecamatan": "Enrekang",
        "Kabupaten": "Kab. Enrekang",
        "Provinsi": "Sulawesi Selatan",
        "Bentuk Koperasi": "Primer Kabupaten/Kota",
        "Jenis Koperasi": "Konsumen",
        "Kelompok Koperasi": "Kop. Veteran",
        "Sektor Usaha": "Jasa Keuangan dan Asuransi",
        "Nama Ketua": "H. Hasim",
        "Nama Sekretaris": "Subirah, S.Pd",
        "Nama Bendahara": "Nurlina",
        "Nama Pengawas": " ",
        "Nama Manager": " ",
        "Jumlah Anggota Pria": "140",
        "Jumlah Anggota Wanita": "63",
        "Total Anggota": "203",
        "Total Manajer": "0",
        "Total Karyawan": "0",
        "Nomor Induk Koperasi (NIK)": "7316020010053",
        "Status NIK": "Sudah Bersertifikat",
        "Tanggal Berlaku Sertifikat": "16/01/2022",
        "Status Grade": "A"
    },
    "7316020050001": {
        "Koperasi": "Koperasi Natiro Mata",
        "Nomor Badan Hukum Pendirian": "4382/BH/IV",
        "Tanggal Badan Hukum Pendirian": "05/07/1984",
        "Nomor Perubahan Anggaran Dasar (Terbaru)": "424/PAD/KWK.20/VI/1997",
        "Tanggal Perubahan Anggaran Dasar (Terbaru)": "10/06/1997",
        "Tanggal RAT Terakhir": "05/08/2021",
        "Alamat": "Jl. Buttu Juppandang No. 41 Enrekang",
        "Kelurahan / Desa": "Juppandang",
        "Kecamatan": "Enrekang",
        "Kabupaten": "Kab. Enrekang",
        "Provinsi": "Sulawesi Selatan",
        "Bentuk Koperasi": "Primer Kabupaten/Kota",
        "Jenis Koperasi": "Simpan Pinjam",
        "Kelompok Koperasi": "Kop. Simpan Pinjam",
        "Sektor Usaha": "Jasa Keuangan dan Asuransi",
        "Nama Ketua": "H.TEha.R",
        "Nama Sekretaris": "Hasir.SE",
        "Nama Bendahara": "Ansar, ST",
        "Nama Pengawas": " ",
        "Nama Manager": " ",
        "Jumlah Anggota Pria": "125",
        "Jumlah Anggota Wanita": "168",
        "Total Anggota": "293",
        "Total Manajer": "0",
        "Total Karyawan": "2",
        "Nomor Induk Koperasi (NIK)": "7316020050001",
        "Status NIK": "Sudah Bersertifikat",
        "Tanggal Berlaku Sertifikat": "05/07/2022",
        "Status Grade": "A"
    },
    "7316020050002": {
        "Koperasi": "Primer Koperasi Angkatan Darat Kodim 1419 Enrekang",
        "Nomor Badan Hukum Pendirian": "4009/BH/IV",
        "Tanggal Badan Hukum Pendirian": "17/01/1997",
        "Nomor Perubahan Anggaran Dasar (Terbaru)": "919/PAD/KWK.20/X/1997",
        "Tanggal Perubahan Anggaran Dasar (Terbaru)": "16/10/1997",
        "Tanggal RAT Terakhir": "30/03/2021",
        "Alamat": "Jl. Pahlawan Enrekang",
        "Kelurahan / Desa": "Juppandang",
        "Kecamatan": "Enrekang",
        "Kabupaten": "Kab. Enrekang",
        "Provinsi": "Sulawesi Selatan",
        "Bentuk Koperasi": "Primer Kabupaten/Kota",
        "Jenis Koperasi": "Konsumen",
        "Kelompok Koperasi": "Kop. Angkatan Darat",
        "Sektor Usaha": "Jasa Keuangan dan Asuransi",
        "Nama Ketua": "Thomas Domeng",
        "Nama Sekretaris": "Ardin",
        "Nama Bendahara": "Derymansa",
        "Nama Pengawas": " ",
        "Nama Manager": " ",
        "Jumlah Anggota Pria": "152",
        "Jumlah Anggota Wanita": "2",
        "Total Anggota": "154",
        "Total Manajer": "0",
        "Total Karyawan": "0",
        "Nomor Induk Koperasi (NIK)": "7316020050002",
        "Status NIK": "Sertifikat - Expired",
        "Tanggal Berlaku Sertifikat": "17/01/2020",
        "Status Grade": "A"
    },
    "7316020050003": {
        "Koperasi": "Koperasi Pkk Crysant Kabupaten Enrekang",
        "Nomor Badan Hukum Pendirian": "90/BH/KDK.20.21/XI/2000",
        "Tanggal Badan Hukum Pendirian": "23/11/2000",
        "Nomor Perubahan Anggaran Dasar (Terbaru)": " ",
        "Tanggal Perubahan Anggaran Dasar (Terbaru)": " ",
        "Tanggal RAT Terakhir": "15/04/2019",
        "Alamat": "Jl. Imam Bonjol",
        "Kelurahan / Desa": "Juppandang",
        "Kecamatan": "Enrekang",
        "Kabupaten": "Kab. Enrekang",
        "Provinsi": "Sulawesi Selatan",
        "Bentuk Koperasi": "Primer Kabupaten/Kota",
        "Jenis Koperasi": "Konsumen",
        "Kelompok Koperasi": "Kop. Wanita",
        "Sektor Usaha": "Jasa Keuangan dan Asuransi",
        "Nama Ketua": "Ny.Hj.Asmarani Amiruddin",
        "Nama Sekretaris": "Indarwati Khairawan, S. Ag, M . Ag",
        "Nama Bendahara": "Dra. Farida Anwar",
        "Nama Pengawas": " ",
        "Nama Manager": " ",
        "Jumlah Anggota Pria": "0",
        "Jumlah Anggota Wanita": "80",
        "Total Anggota": "80",
        "Total Manajer": "0",
        "Total Karyawan": "0",
        "Nomor Induk Koperasi (NIK)": "7316020050003",
        "Status NIK": "Sertifikat - Expired",
        "Tanggal Berlaku Sertifikat": "23/11/2020",
        "Status Grade": "B"
    },
    "7316020050004": {
        "Koperasi": "Koperasi Karya Bersama Maspul",
        "Nomor Badan Hukum Pendirian": "145/BH/XXIV.4/IV/2011",
        "Tanggal Badan Hukum Pendirian": "09/04/2011",
        "Nomor Perubahan Anggaran Dasar (Terbaru)": " ",
        "Tanggal Perubahan Anggaran Dasar (Terbaru)": " ",
        "Tanggal RAT Terakhir": "27/02/2020",
        "Alamat": "Jl. Pahlawan Enrekang",
        "Kelurahan / Desa": "Juppandang",
        "Kecamatan": "Enrekang",
        "Kabupaten": "Kab. Enrekang",
        "Provinsi": "Sulawesi Selatan",
        "Bentuk Koperasi": "Primer Kabupaten/Kota",
        "Jenis Koperasi": "Simpan Pinjam",
        "Kelompok Koperasi": "Kop. Simpan Pinjam",
        "Sektor Usaha": "Jasa Keuangan dan Asuransi",
        "Nama Ketua": "Hj.ST.Halifa Bando,S.IP",
        "Nama Sekretaris": " ",
        "Nama Bendahara": "Dukumia",
        "Nama Pengawas": " ",
        "Nama Manager": " ",
        "Jumlah Anggota Pria": "57",
        "Jumlah Anggota Wanita": "7",
        "Total Anggota": "64",
        "Total Manajer": "0",
        "Total Karyawan": "0",
        "Nomor Induk Koperasi (NIK)": "7316020050004",
        "Status NIK": "Sertifikat - Expired",
        "Tanggal Berlaku Sertifikat": "09/04/2020",
        "Status Grade": "A"
    },
    "7316020050005": {
        "Koperasi": "Koperasi Simpan Pinjam Masyarakat Enrekang",
        "Nomor Badan Hukum Pendirian": "3488/BH/IV",
        "Tanggal Badan Hukum Pendirian": "05/04/1971",
        "Nomor Perubahan Anggaran Dasar (Terbaru)": "524/PAD/KWK.20/VII/1997",
        "Tanggal Perubahan Anggaran Dasar (Terbaru)": "14/07/1997",
        "Tanggal RAT Terakhir": "03/06/2021",
        "Alamat": "Jl. Pasar Sentral No. 05 Enrekang",
        "Kelurahan / Desa": "Juppandang",
        "Kecamatan": "Enrekang",
        "Kabupaten": "Kab. Enrekang",
        "Provinsi": "Sulawesi Selatan",
        "Bentuk Koperasi": "Primer Kabupaten/Kota",
        "Jenis Koperasi": "Simpan Pinjam",
        "Kelompok Koperasi": "Kop. Simpan Pinjam",
        "Sektor Usaha": "Jasa Keuangan dan Asuransi",
        "Nama Ketua": "M.ramli Latman,SE,ST",
        "Nama Sekretaris": "Darna,SE",
        "Nama Bendahara": "Heli Novianti",
        "Nama Pengawas": " ",
        "Nama Manager": " ",
        "Jumlah Anggota Pria": "10",
        "Jumlah Anggota Wanita": "30",
        "Total Anggota": "40",
        "Total Manajer": "0",
        "Total Karyawan": "0",
        "Nomor Induk Koperasi (NIK)": "7316020050005",
        "Status NIK": "Sertifikat - Expired",
        "Tanggal Berlaku Sertifikat": "05/04/2020",
        "Status Grade": "A"
    },
    "7316020050006": {
        "Koperasi": "Koperasi Pegawai Negeri SMEA PGRI",
        "Nomor Badan Hukum Pendirian": "5165/BH/IV",
        "Tanggal Badan Hukum Pendirian": "18/03/1991",
        "Nomor Perubahan Anggaran Dasar (Terbaru)": "443/PAD/KWK.20/VI/1997",
        "Tanggal Perubahan Anggaran Dasar (Terbaru)": "10/06/1997",
        "Tanggal RAT Terakhir": "06/04/2020",
        "Alamat": "Enrekang Kelurahan Juppandang",
        "Kelurahan / Desa": "Kelurahan Juppandang",
        "Kecamatan": "Enrekang",
        "Kabupaten": "Kab. Enrekang",
        "Provinsi": "Sulawesi Selatan",
        "Bentuk Koperasi": "Primer Kabupaten/Kota",
        "Jenis Koperasi": "Konsumen",
        "Kelompok Koperasi": "Kop. Pegawai Negeri (KPRI)",
        "Sektor Usaha": "Jasa Keuangan dan Asuransi",
        "Nama Ketua": "Nurhidayah,S.Pd",
        "Nama Sekretaris": "M.Idris Gusti,BSc",
        "Nama Bendahara": "Mahmud, SE",
        "Nama Pengawas": " ",
        "Nama Manager": " ",
        "Jumlah Anggota Pria": "20",
        "Jumlah Anggota Wanita": "27",
        "Total Anggota": "47",
        "Total Manajer": "0",
        "Total Karyawan": "0",
        "Nomor Induk Koperasi (NIK)": "7316020050006",
        "Status NIK": "Sertifikat - Expired",
        "Tanggal Berlaku Sertifikat": "18/03/2021",
        "Status Grade": "A"
    },
    "7316020050007": {
        "Koperasi": "Koperasi Syariah BMT Al Istiqomah",
        "Nomor Badan Hukum Pendirian": "109/KEP-BH/PPD/2.1/IX/2004",
        "Tanggal Badan Hukum Pendirian": "09/09/2004",
        "Nomor Perubahan Anggaran Dasar (Terbaru)": " ",
        "Tanggal Perubahan Anggaran Dasar (Terbaru)": " ",
        "Tanggal RAT Terakhir": "26/02/2020",
        "Alamat": "Jl. Industri No. 26",
        "Kelurahan / Desa": "Juppandang",
        "Kecamatan": "Enrekang",
        "Kabupaten": "Kab. Enrekang",
        "Provinsi": "Sulawesi Selatan",
        "Bentuk Koperasi": "Primer Kabupaten/Kota",
        "Jenis Koperasi": "Konsumen",
        "Kelompok Koperasi": "Kop. Simpan Pinjam dan Pembiayaan Syariah",
        "Sektor Usaha": "Jasa Keuangan dan Asuransi",
        "Nama Ketua": "Dra. Bina Tabi",
        "Nama Sekretaris": "Sri Muliati Yusuf , SE",
        "Nama Bendahara": "Hj. Ekayanti",
        "Nama Pengawas": " ",
        "Nama Manager": " ",
        "Jumlah Anggota Pria": "49",
        "Jumlah Anggota Wanita": "120",
        "Total Anggota": "169",
        "Total Manajer": "0",
        "Total Karyawan": "0",
        "Nomor Induk Koperasi (NIK)": "7316020050007",
        "Status NIK": "Sertifikat - Expired",
        "Tanggal Berlaku Sertifikat": "09/09/2020",
        "Status Grade": "A"
    },
    "7316020150001": {
        "Koperasi": "Koperasi Pegawai Negeri Guru - Guru SMP Negeri Temban",
        "Nomor Badan Hukum Pendirian": "5306/BH/IV",
        "Tanggal Badan Hukum Pendirian": "06/11/1992",
        "Nomor Perubahan Anggaran Dasar (Terbaru)": "447/PAD/KWK.20/VI/1997",
        "Tanggal Perubahan Anggaran Dasar (Terbaru)": "10/06/1997",
        "Tanggal RAT Terakhir": "27/01/2021",
        "Alamat": "Desa Temban",
        "Kelurahan / Desa": "Desa Temban",
        "Kecamatan": "Enrekang",
        "Kabupaten": "Kab. Enrekang",
        "Provinsi": "Sulawesi Selatan",
        "Bentuk Koperasi": "Primer Kabupaten/Kota",
        "Jenis Koperasi": "Konsumen",
        "Kelompok Koperasi": "Kop. Pegawai Negeri (KPRI)",
        "Sektor Usaha": "Jasa Keuangan dan Asuransi",
        "Nama Ketua": "Mahmud, S.Pd",
        "Nama Sekretaris": "Drs. Hasan",
        "Nama Bendahara": "Nurhaedah",
        "Nama Pengawas": " ",
        "Nama Manager": " ",
        "Jumlah Anggota Pria": "23",
        "Jumlah Anggota Wanita": "35",
        "Total Anggota": "58",
        "Total Manajer": "0",
        "Total Karyawan": "0",
        "Nomor Induk Koperasi (NIK)": "7316020150001",
        "Status NIK": "Sertifikat - Expired",
        "Tanggal Berlaku Sertifikat": "06/11/2020",
        "Status Grade": "A"
    },
    "7316020200001": {
        "Koperasi": "Koperasi Pegawai Negeri Sekolah Menengah Umum Negeri 374 Enrekang",
        "Nomor Badan Hukum Pendirian": "4585/BH/IV",
        "Tanggal Badan Hukum Pendirian": "19/11/1986",
        "Nomor Perubahan Anggaran Dasar (Terbaru)": "506/PAD/KWK.20/VII/1997",
        "Tanggal Perubahan Anggaran Dasar (Terbaru)": "10/07/1997",
        "Tanggal RAT Terakhir": "24/02/2021",
        "Alamat": "Jl. Jenderal Sudirman No.09",
        "Kelurahan / Desa": "Galonta",
        "Kecamatan": "Enrekang",
        "Kabupaten": "Kab. Enrekang",
        "Provinsi": "Sulawesi Selatan",
        "Bentuk Koperasi": "Primer Kabupaten/Kota",
        "Jenis Koperasi": "Konsumen",
        "Kelompok Koperasi": "Kop. Pegawai Negeri (KPRI)",
        "Sektor Usaha": "Jasa Keuangan dan Asuransi",
        "Nama Ketua": "Talib L, S.Pd., M.pd",
        "Nama Sekretaris": "Jusmiati, S.Pd",
        "Nama Bendahara": "Suherna Amad, S.Pd",
        "Nama Pengawas": " ",
        "Nama Manager": " ",
        "Jumlah Anggota Pria": "20",
        "Jumlah Anggota Wanita": "25",
        "Total Anggota": "45",
        "Total Manajer": "0",
        "Total Karyawan": "0",
        "Nomor Induk Koperasi (NIK)": "7316020200001",
        "Status NIK": "Sertifikat - Expired",
        "Tanggal Berlaku Sertifikat": "19/11/2020",
        "Status Grade": "A"
    },
    "7316020200002": {
        "Koperasi": "Koperasi Pegawai Negeri SMP Negeri 1 Enrekang",
        "Nomor Badan Hukum Pendirian": "4308/BH/IV",
        "Tanggal Badan Hukum Pendirian": "21/10/1983",
        "Nomor Perubahan Anggaran Dasar (Terbaru)": "441/PAD/KWK.20/VI/1997",
        "Tanggal Perubahan Anggaran Dasar (Terbaru)": "10/06/1997",
        "Tanggal RAT Terakhir": "10/03/2021",
        "Alamat": "Jl. Jenderal Sudirman No. 3",
        "Kelurahan / Desa": "Galonta",
        "Kecamatan": "Enrekang",
        "Kabupaten": "Kab. Enrekang",
        "Provinsi": "Sulawesi Selatan",
        "Bentuk Koperasi": "Primer Kabupaten/Kota",
        "Jenis Koperasi": "Konsumen",
        "Kelompok Koperasi": "Kop. Pegawai Negeri (KPRI)",
        "Sektor Usaha": "Jasa Keuangan dan Asuransi",
        "Nama Ketua": "Hamzah B, S. Pd",
        "Nama Sekretaris": "Sudarman, S. Pd",
        "Nama Bendahara": "Hafsah, S. Pd",
        "Nama Pengawas": " ",
        "Nama Manager": " ",
        "Jumlah Anggota Pria": "20",
        "Jumlah Anggota Wanita": "32",
        "Total Anggota": "52",
        "Total Manajer": "0",
        "Total Karyawan": "0",
        "Nomor Induk Koperasi (NIK)": "7316020200002",
        "Status NIK": "Sertifikat - Expired",
        "Tanggal Berlaku Sertifikat": "21/10/2020",
        "Status Grade": "A"
    },
    "7316020200003": {
        "Koperasi": "Koperasi Pengayoman Pegawai Departemen Kehakiman PN Kab Enrekang",
        "Nomor Badan Hukum Pendirian": "5112/BH/IV",
        "Tanggal Badan Hukum Pendirian": "24/09/1990",
        "Nomor Perubahan Anggaran Dasar (Terbaru)": "425/PAD/KWK.20/VI/1997",
        "Tanggal Perubahan Anggaran Dasar (Terbaru)": "10/06/1997",
        "Tanggal RAT Terakhir": "25/06/2021",
        "Alamat": "Jl. Lasinrang No 2 enrekang",
        "Kelurahan / Desa": "Galonta",
        "Kecamatan": "Enrekang",
        "Kabupaten": "Kab. Enrekang",
        "Provinsi": "Sulawesi Selatan",
        "Bentuk Koperasi": "Primer Kabupaten/Kota",
        "Jenis Koperasi": "Konsumen",
        "Kelompok Koperasi": "Kop. Pegawai Negeri (KPRI)",
        "Sektor Usaha": "Jasa Keuangan dan Asuransi",
        "Nama Ketua": "Anwar,S.Pd.SH",
        "Nama Sekretaris": "Sulastri Sapar,SH",
        "Nama Bendahara": "Muhlis,SH",
        "Nama Pengawas": " ",
        "Nama Manager": " ",
        "Jumlah Anggota Pria": "22",
        "Jumlah Anggota Wanita": "6",
        "Total Anggota": "28",
        "Total Manajer": "0",
        "Total Karyawan": "0",
        "Nomor Induk Koperasi (NIK)": "7316020200003",
        "Status NIK": "Sertifikat - Expired",
        "Tanggal Berlaku Sertifikat": "24/09/2020",
        "Status Grade": "A"
    },
    "7316020200018": {
        "Koperasi": "Koperasi Pegawai Negeri Dinas Peternakan",
        "Nomor Badan Hukum Pendirian": "4486/BH/IV",
        "Tanggal Badan Hukum Pendirian": "05/12/1985",
        "Nomor Perubahan Anggaran Dasar (Terbaru)": "448/PAD/KWK.20/VI/1997",
        "Tanggal Perubahan Anggaran Dasar (Terbaru)": "10/06/1997",
        "Tanggal RAT Terakhir": "12/04/2019",
        "Alamat": "Enrekang",
        "Kelurahan / Desa": "Kelurahan Galonta",
        "Kecamatan": "Enrekang",
        "Kabupaten": "Kab. Enrekang",
        "Provinsi": "Sulawesi Selatan",
        "Bentuk Koperasi": "Primer Kabupaten/Kota",
        "Jenis Koperasi": "Konsumen",
        "Kelompok Koperasi": "Kop. Pegawai Negeri (KPRI)",
        "Sektor Usaha": "Jasa Keuangan dan Asuransi",
        "Nama Ketua": "Hartono.S.ST",
        "Nama Sekretaris": "Mustamin, S. Sos",
        "Nama Bendahara": "Suryanti.S.Pt",
        "Nama Pengawas": " ",
        "Nama Manager": " ",
        "Jumlah Anggota Pria": "37",
        "Jumlah Anggota Wanita": "39",
        "Total Anggota": "76",
        "Total Manajer": "0",
        "Total Karyawan": "2",
        "Nomor Induk Koperasi (NIK)": "7316020200018",
        "Status NIK": "Sertifikat - Expired",
        "Tanggal Berlaku Sertifikat": "05/12/2019",
        "Status Grade": "B"
    },
    "7316020050034": {
        "Koperasi": "Koperasi Karyawan Tomaloga BRI",
        "Nomor Badan Hukum Pendirian": "4608/BH/IV",
        "Tanggal Badan Hukum Pendirian": "16/12/1986",
        "Nomor Perubahan Anggaran Dasar (Terbaru)": "921/PAD/KWK.20/X/1997",
        "Tanggal Perubahan Anggaran Dasar (Terbaru)": "16/10/1997",
        "Tanggal RAT Terakhir": "20/08/2021",
        "Alamat": "Jl. Hos Cokroaminoto No. 01",
        "Kelurahan / Desa": "Juppandang",
        "Kecamatan": "Enrekang",
        "Kabupaten": "Kab. Enrekang",
        "Provinsi": "Sulawesi Selatan",
        "Bentuk Koperasi": "Primer Kabupaten/Kota",
        "Jenis Koperasi": "Konsumen",
        "Kelompok Koperasi": "Kopkar",
        "Sektor Usaha": "Jasa Keuangan dan Asuransi",
        "Nama Ketua": "Muh.Ardani Ibrahim",
        "Nama Sekretaris": "Muh. Fadli Djannatin",
        "Nama Bendahara": "Marchelin Arung TR",
        "Nama Pengawas": " ",
        "Nama Manager": " ",
        "Jumlah Anggota Pria": "145",
        "Jumlah Anggota Wanita": "50",
        "Total Anggota": "195",
        "Total Manajer": "0",
        "Total Karyawan": "2",
        "Nomor Induk Koperasi (NIK)": "7316020050034",
        "Status NIK": "Sudah Bersertifikat",
        "Tanggal Berlaku Sertifikat": "16/12/2022",
        "Status Grade": "A"
    },
    "7316020110002": {
        "Koperasi": "Koperasi Pegawai Negeri Kantor Departemen Agama",
        "Nomor Badan Hukum Pendirian": "4730/BH/IV",
        "Tanggal Badan Hukum Pendirian": "15/08/1987",
        "Nomor Perubahan Anggaran Dasar (Terbaru)": "419/PAD/KWK.20/VI/1997",
        "Tanggal Perubahan Anggaran Dasar (Terbaru)": "10/06/1997",
        "Tanggal RAT Terakhir": "05/01/2021",
        "Alamat": "Jl. Sultan Hasanuddin No. 113",
        "Kelurahan / Desa": "Puserren",
        "Kecamatan": "Enrekang",
        "Kabupaten": "Kab. Enrekang",
        "Provinsi": "Sulawesi Selatan",
        "Bentuk Koperasi": "Primer Kabupaten/Kota",
        "Jenis Koperasi": "Konsumen",
        "Kelompok Koperasi": "Kop. Pegawai Negeri (KPRI)",
        "Sektor Usaha": "Jasa Keuangan dan Asuransi",
        "Nama Ketua": "Drs.H.Syawal,M.Ag",
        "Nama Sekretaris": "Arifullajalli Busra S.Pd.I",
        "Nama Bendahara": "Muna,ST",
        "Nama Pengawas": " ",
        "Nama Manager": " ",
        "Jumlah Anggota Pria": "91",
        "Jumlah Anggota Wanita": "107",
        "Total Anggota": "198",
        "Total Manajer": "0",
        "Total Karyawan": "0",
        "Nomor Induk Koperasi (NIK)": "7316020110002",
        "Status NIK": "Sertifikat - Expired",
        "Tanggal Berlaku Sertifikat": "15/08/2020",
        "Status Grade": "A"
    },
    "7316020110043": {
        "Koperasi": "Primer Koperasi Kepolisian Resort Enrekang",
        "Nomor Badan Hukum Pendirian": "3749/BH/IV",
        "Tanggal Badan Hukum Pendirian": "31/08/1974",
        "Nomor Perubahan Anggaran Dasar (Terbaru)": "21/PAD/KWK.20/XII/1995",
        "Tanggal Perubahan Anggaran Dasar (Terbaru)": "28/12/1995",
        "Tanggal RAT Terakhir": "30/09/2021",
        "Alamat": "Jl. Sultan Hasanuddin No. 40 Enrekang",
        "Kelurahan / Desa": "Puserren",
        "Kecamatan": "Enrekang",
        "Kabupaten": "Kab. Enrekang",
        "Provinsi": "Sulawesi Selatan",
        "Bentuk Koperasi": "Primer Kabupaten/Kota",
        "Jenis Koperasi": "Konsumen",
        "Kelompok Koperasi": "Kop. Kepolisian",
        "Sektor Usaha": "Jasa Keuangan dan Asuransi",
        "Nama Ketua": "Syafruddin",
        "Nama Sekretaris": "Rusdin",
        "Nama Bendahara": "Aries Nugroho,SE",
        "Nama Pengawas": " ",
        "Nama Manager": " ",
        "Jumlah Anggota Pria": "314",
        "Jumlah Anggota Wanita": "14",
        "Total Anggota": "328",
        "Total Manajer": "0",
        "Total Karyawan": "3",
        "Nomor Induk Koperasi (NIK)": "7316020110043",
        "Status NIK": "Sertifikat - Expired",
        "Tanggal Berlaku Sertifikat": "31/08/2019",
        "Status Grade": "A"
    },
    "7316040020002": {
        "Koperasi": "Koperasi Pegawai Negeri Sekolah Menengah Pertama Negeri Kotu",
        "Nomor Badan Hukum Pendirian": "4996/BH/IV",
        "Tanggal Badan Hukum Pendirian": "15/09/1989",
        "Nomor Perubahan Anggaran Dasar (Terbaru)": "442/PAD/KWK.20/VI/1997",
        "Tanggal Perubahan Anggaran Dasar (Terbaru)": "10/06/1997",
        "Tanggal RAT Terakhir": "21/06/2021",
        "Alamat": "Kotu Bamba Puang",
        "Kelurahan / Desa": "Desa Bamba Puang",
        "Kecamatan": "Anggeraja",
        "Kabupaten": "Kab. Enrekang",
        "Provinsi": "Sulawesi Selatan",
        "Bentuk Koperasi": "Primer Kabupaten/Kota",
        "Jenis Koperasi": "Konsumen",
        "Kelompok Koperasi": "Kop. Pegawai Negeri (KPRI)",
        "Sektor Usaha": "Jasa Keuangan dan Asuransi",
        "Nama Ketua": "Zainuddin,S.Pd",
        "Nama Sekretaris": "Saharuddin.S.Pd",
        "Nama Bendahara": "Alimuddin.S.Pd",
        "Nama Pengawas": " ",
        "Nama Manager": " ",
        "Jumlah Anggota Pria": "39",
        "Jumlah Anggota Wanita": "95",
        "Total Anggota": "134",
        "Total Manajer": "0",
        "Total Karyawan": "0",
        "Nomor Induk Koperasi (NIK)": "7316040020002",
        "Status NIK": "Sudah Bersertifikat",
        "Tanggal Berlaku Sertifikat": "15/09/2022",
        "Status Grade": "A"
    },
    "7316040050001": {
        "Koperasi": "Koperasi Serba Usaha Mario Marannu 45",
        "Nomor Badan Hukum Pendirian": "89/BH/KDK.20.21/XI/2000",
        "Tanggal Badan Hukum Pendirian": "13/11/2000",
        "Nomor Perubahan Anggaran Dasar (Terbaru)": " ",
        "Tanggal Perubahan Anggaran Dasar (Terbaru)": " ",
        "Tanggal RAT Terakhir": "11/02/2021",
        "Alamat": "Cakke",
        "Kelurahan / Desa": "Lakawan",
        "Kecamatan": "Anggeraja",
        "Kabupaten": "Kab. Enrekang",
        "Provinsi": "Sulawesi Selatan",
        "Bentuk Koperasi": "Primer Kabupaten/Kota",
        "Jenis Koperasi": "Konsumen",
        "Kelompok Koperasi": "Kop. Serba Usaha",
        "Sektor Usaha": "Jasa Keuangan dan Asuransi",
        "Nama Ketua": "Drs. Samudra",
        "Nama Sekretaris": "Sitti Ramlah, S.Pd",
        "Nama Bendahara": "Mastarang, S.Pd",
        "Nama Pengawas": " ",
        "Nama Manager": " ",
        "Jumlah Anggota Pria": "16",
        "Jumlah Anggota Wanita": "30",
        "Total Anggota": "46",
        "Total Manajer": "0",
        "Total Karyawan": "0",
        "Nomor Induk Koperasi (NIK)": "7316040050001",
        "Status NIK": "Sertifikat - Expired",
        "Tanggal Berlaku Sertifikat": "13/11/2020",
        "Status Grade": "A"
    },
    "7316040080001": {
        "Koperasi": "Koperasi Simpan Pinjam Enrekang Abadi Sejahtera",
        "Nomor Badan Hukum Pendirian": "005615/BH/M.KUKM.2/X/2017",
        "Tanggal Badan Hukum Pendirian": "11/10/2017",
        "Nomor Perubahan Anggaran Dasar (Terbaru)": " ",
        "Tanggal Perubahan Anggaran Dasar (Terbaru)": " ",
        "Tanggal RAT Terakhir": "23/03/2021",
        "Alamat": "Jl. Poros Makassar Tator Kelurahan Mataran",
        "Kelurahan / Desa": "Kelurahan Mataran",
        "Kecamatan": "Anggeraja",
        "Kabupaten": "Kab. Enrekang",
        "Provinsi": "Sulawesi Selatan",
        "Bentuk Koperasi": "Primer Kabupaten/Kota",
        "Jenis Koperasi": "Simpan Pinjam",
        "Kelompok Koperasi": "Kop. Simpan Pinjam",
        "Sektor Usaha": "Jasa Keuangan dan Asuransi",
        "Nama Ketua": "Abd. Rasyid",
        "Nama Sekretaris": "Wardana",
        "Nama Bendahara": "Sri Nur Sahruni",
        "Nama Pengawas": " ",
        "Nama Manager": " ",
        "Jumlah Anggota Pria": "149",
        "Jumlah Anggota Wanita": "443",
        "Total Anggota": "592",
        "Total Manajer": "0",
        "Total Karyawan": "0",
        "Nomor Induk Koperasi (NIK)": "7316040080001",
        "Status NIK": "Sertifikat - Expired",
        "Tanggal Berlaku Sertifikat": "11/10/2021",
        "Status Grade": "A"
    },
    "7316040130001": {
        "Koperasi": "Koperasi Siambo Cendana",
        "Nomor Badan Hukum Pendirian": "134/BH/XXIV.4/XII/2007",
        "Tanggal Badan Hukum Pendirian": "30/12/2007",
        "Nomor Perubahan Anggaran Dasar (Terbaru)": " ",
        "Tanggal Perubahan Anggaran Dasar (Terbaru)": " ",
        "Tanggal RAT Terakhir": "12/01/2021",
        "Alamat": "Cendana",
        "Kelurahan / Desa": "Desa Siambo",
        "Kecamatan": "Anggeraja",
        "Kabupaten": "Kab. Enrekang",
        "Provinsi": "Sulawesi Selatan",
        "Bentuk Koperasi": "Primer Kabupaten/Kota",
        "Jenis Koperasi": "Konsumen",
        "Kelompok Koperasi": "Kop. Pegawai Negeri (KPRI)",
        "Sektor Usaha": "Jasa Keuangan dan Asuransi",
        "Nama Ketua": "Halias, S.Pd",
        "Nama Sekretaris": "Sahid, S.Pd",
        "Nama Bendahara": "Rusni Tahir , S.Pd",
        "Nama Pengawas": " ",
        "Nama Manager": " ",
        "Jumlah Anggota Pria": "10",
        "Jumlah Anggota Wanita": "13",
        "Total Anggota": "23",
        "Total Manajer": "0",
        "Total Karyawan": "0",
        "Nomor Induk Koperasi (NIK)": "7316040130001",
        "Status NIK": "Sertifikat - Expired",
        "Tanggal Berlaku Sertifikat": "30/12/2020",
        "Status Grade": "A"
    },
    "7316040140002": {
        "Koperasi": "Koperasi Unit Desa Singki",
        "Nomor Badan Hukum Pendirian": "5434/BH/IV",
        "Tanggal Badan Hukum Pendirian": "03/05/1994",
        "Nomor Perubahan Anggaran Dasar (Terbaru)": "-",
        "Tanggal Perubahan Anggaran Dasar (Terbaru)": " ",
        "Tanggal RAT Terakhir": " ",
        "Alamat": "Desa Singki",
        "Kelurahan / Desa": "Desa Singki",
        "Kecamatan": "Anggeraja",
        "Kabupaten": "Kab. Enrekang",
        "Provinsi": "Sulawesi Selatan",
        "Bentuk Koperasi": "Primer Kabupaten/Kota",
        "Jenis Koperasi": "Produsen",
        "Kelompok Koperasi": "KUD",
        "Sektor Usaha": "Pertanian, Kehutanan dan Perikanan",
        "Nama Ketua": "Abd. Asis, S. Pd",
        "Nama Sekretaris": "Mahlis jasman,S.Pd",
        "Nama Bendahara": "Kasmin",
        "Nama Pengawas": " ",
        "Nama Manager": " ",
        "Jumlah Anggota Pria": "453",
        "Jumlah Anggota Wanita": "65",
        "Total Anggota": "518",
        "Total Manajer": "1",
        "Total Karyawan": "11",
        "Nomor Induk Koperasi (NIK)": "7316040140002",
        "Status NIK": "Sertifikat - Expired",
        "Tanggal Berlaku Sertifikat": "02/05/2019",
        "Status Grade": "A"
    },
    "7316050040001": {
        "Koperasi": "Koperasi Pegawai Negeri Sipakaraja",
        "Nomor Badan Hukum Pendirian": "113/KEP-BH/PPR/2.1/XII/2004",
        "Tanggal Badan Hukum Pendirian": "17/12/2004",
        "Nomor Perubahan Anggaran Dasar (Terbaru)": " ",
        "Tanggal Perubahan Anggaran Dasar (Terbaru)": " ",
        "Tanggal RAT Terakhir": "27/05/2021",
        "Alamat": "Jl. Ahmad Yani Kalosi",
        "Kelurahan / Desa": "Kelurahan Kalosi",
        "Kecamatan": "Alla",
        "Kabupaten": "Kab. Enrekang",
        "Provinsi": "Sulawesi Selatan",
        "Bentuk Koperasi": "Primer Kabupaten/Kota",
        "Jenis Koperasi": "Jasa",
        "Kelompok Koperasi": "Kop. Pegawai Negeri (KPRI)",
        "Sektor Usaha": "Jasa Keuangan dan Asuransi",
        "Nama Ketua": "Sadar Lengo, S.Pd",
        "Nama Sekretaris": "Buhari Baramang, S.Pd",
        "Nama Bendahara": "Rawasih, S.Pd",
        "Nama Pengawas": " ",
        "Nama Manager": " ",
        "Jumlah Anggota Pria": "14",
        "Jumlah Anggota Wanita": "24",
        "Total Anggota": "38",
        "Total Manajer": "0",
        "Total Karyawan": "0",
        "Nomor Induk Koperasi (NIK)": "7316050040001",
        "Status NIK": "Sertifikat - Expired",
        "Tanggal Berlaku Sertifikat": "17/12/2021",
        "Status Grade": "A"
    },
    "7316050050001": {
        "Koperasi": "KPN Kantor Departemen Pendidikan dan Kebudayaan Kec Alla",
        "Nomor Badan Hukum Pendirian": "5439/BH/IV",
        "Tanggal Badan Hukum Pendirian": "23/05/1994",
        "Nomor Perubahan Anggaran Dasar (Terbaru)": "138/BH/XXIV.4/IV/2010",
        "Tanggal Perubahan Anggaran Dasar (Terbaru)": "29/04/2010",
        "Tanggal RAT Terakhir": "08/08/2019",
        "Alamat": "Belajen",
        "Kelurahan / Desa": "Kambiolangi",
        "Kecamatan": "Alla",
        "Kabupaten": "Kab. Enrekang",
        "Provinsi": "Sulawesi Selatan",
        "Bentuk Koperasi": "Primer Kabupaten/Kota",
        "Jenis Koperasi": "Konsumen",
        "Kelompok Koperasi": "Kop. Pegawai Negeri (KPRI)",
        "Sektor Usaha": "Jasa Keuangan dan Asuransi",
        "Nama Ketua": "Amri, S.Pd",
        "Nama Sekretaris": "Jasman, S. Pd, M. Pd",
        "Nama Bendahara": "Lukman, S. Pd, M. Pd",
        "Nama Pengawas": " ",
        "Nama Manager": " ",
        "Jumlah Anggota Pria": "63",
        "Jumlah Anggota Wanita": "95",
        "Total Anggota": "158",
        "Total Manajer": "0",
        "Total Karyawan": "0",
        "Nomor Induk Koperasi (NIK)": "7316050050001",
        "Status NIK": "Sertifikat - Expired",
        "Tanggal Berlaku Sertifikat": "23/05/2020",
        "Status Grade": "B"
    },
    "7316050050002": {
        "Koperasi": "Koperasi Simpan Pinjam Lestari",
        "Nomor Badan Hukum Pendirian": "75/BH/KWK.20/VI/1996",
        "Tanggal Badan Hukum Pendirian": "17/06/1996",
        "Nomor Perubahan Anggaran Dasar (Terbaru)": " ",
        "Tanggal Perubahan Anggaran Dasar (Terbaru)": " ",
        "Tanggal RAT Terakhir": "25/03/2021",
        "Alamat": "Jl. Jenderal Ahmad Yani Sudu",
        "Kelurahan / Desa": "Kambiolangi",
        "Kecamatan": "Alla",
        "Kabupaten": "Kab. Enrekang",
        "Provinsi": "Sulawesi Selatan",
        "Bentuk Koperasi": "Primer Kabupaten/Kota",
        "Jenis Koperasi": "Simpan Pinjam",
        "Kelompok Koperasi": "Kop. Simpan Pinjam",
        "Sektor Usaha": "Jasa Keuangan dan Asuransi",
        "Nama Ketua": "Ruslan,SH",
        "Nama Sekretaris": "Hasrul",
        "Nama Bendahara": "Marwati",
        "Nama Pengawas": " ",
        "Nama Manager": " ",
        "Jumlah Anggota Pria": "228",
        "Jumlah Anggota Wanita": "218",
        "Total Anggota": "446",
        "Total Manajer": "0",
        "Total Karyawan": "0",
        "Nomor Induk Koperasi (NIK)": "7316050050002",
        "Status NIK": "Sertifikat - Expired",
        "Tanggal Berlaku Sertifikat": "17/06/2020",
        "Status Grade": "A"
    },
    "7316050050003": {
        "Koperasi": "Koperasi Unit Desa Kambiolangi",
        "Nomor Badan Hukum Pendirian": "4038/BH/IV/1983",
        "Tanggal Badan Hukum Pendirian": "15/08/1983",
        "Nomor Perubahan Anggaran Dasar (Terbaru)": "66/PAD/KWK.20/V/1996",
        "Tanggal Perubahan Anggaran Dasar (Terbaru)": "07/05/1996",
        "Tanggal RAT Terakhir": "18/06/2021",
        "Alamat": "Belajen Kelurahan Kambiolangi",
        "Kelurahan / Desa": "Kelurahan Kambiolangi",
        "Kecamatan": "Alla",
        "Kabupaten": "Kab. Enrekang",
        "Provinsi": "Sulawesi Selatan",
        "Bentuk Koperasi": "Primer Kabupaten/Kota",
        "Jenis Koperasi": "Pemasaran",
        "Kelompok Koperasi": "KUD",
        "Sektor Usaha": "Perdagangan Besar dan Eceran - Rep Mobil dan Motor",
        "Nama Ketua": "Drs. H. Sawal Sitonda, M.Ag",
        "Nama Sekretaris": "Drs. H. Sampe Lemang, M. Pd",
        "Nama Bendahara": "Rajono",
        "Nama Pengawas": " ",
        "Nama Manager": " ",
        "Jumlah Anggota Pria": "202",
        "Jumlah Anggota Wanita": "83",
        "Total Anggota": "285",
        "Total Manajer": "0",
        "Total Karyawan": "0",
        "Nomor Induk Koperasi (NIK)": "7316050050003",
        "Status NIK": "Sertifikat - Expired",
        "Tanggal Berlaku Sertifikat": "15/08/2021",
        "Status Grade": "A"
    },
    "7316060020001": {
        "Koperasi": "Koperasi Pegawai Negeri Guru - Guru SMP Negeri Baba",
        "Nomor Badan Hukum Pendirian": "4652/BH/IV",
        "Tanggal Badan Hukum Pendirian": "18/03/1987",
        "Nomor Perubahan Anggaran Dasar (Terbaru)": "449/PAD/KWK.20/VI/1997",
        "Tanggal Perubahan Anggaran Dasar (Terbaru)": " ",
        "Tanggal RAT Terakhir": "15/04/2019",
        "Alamat": "Baba Desa Cendana",
        "Kelurahan / Desa": "Desa Cendana",
        "Kecamatan": "Cendana",
        "Kabupaten": "Kab. Enrekang",
        "Provinsi": "Sulawesi Selatan",
        "Bentuk Koperasi": "Primer Kabupaten/Kota",
        "Jenis Koperasi": "Konsumen",
        "Kelompok Koperasi": "Kop. Pegawai Negeri (KPRI)",
        "Sektor Usaha": "Jasa Keuangan dan Asuransi",
        "Nama Ketua": "Ahmad magga,S.Pd",
        "Nama Sekretaris": "M.Rais,S.Ag",
        "Nama Bendahara": "Lahata,S.Pd",
        "Nama Pengawas": " ",
        "Nama Manager": " ",
        "Jumlah Anggota Pria": "8",
        "Jumlah Anggota Wanita": "7",
        "Total Anggota": "15",
        "Total Manajer": "0",
        "Total Karyawan": "3",
        "Nomor Induk Koperasi (NIK)": "7316060020001",
        "Status NIK": "Sertifikat - Expired",
        "Tanggal Berlaku Sertifikat": "18/03/2020",
        "Status Grade": "B"
    },
    "7316060080001": {
        "Koperasi": "Koperasi Unit Desa Cendana",
        "Nomor Badan Hukum Pendirian": "4309/BH/IV",
        "Tanggal Badan Hukum Pendirian": "15/08/1983",
        "Nomor Perubahan Anggaran Dasar (Terbaru)": "115/PAD/KWK.20/VI/1996",
        "Tanggal Perubahan Anggaran Dasar (Terbaru)": "20/06/1996",
        "Tanggal RAT Terakhir": "29/04/2020",
        "Alamat": "Jl. Ahmad Yani No. 14 Kabere",
        "Kelurahan / Desa": "Desa Taulan",
        "Kecamatan": "Cendana",
        "Kabupaten": "Kab. Enrekang",
        "Provinsi": "Sulawesi Selatan",
        "Bentuk Koperasi": "Primer Kabupaten/Kota",
        "Jenis Koperasi": "Konsumen",
        "Kelompok Koperasi": "KUD",
        "Sektor Usaha": "Perdagangan Besar dan Eceran - Rep Mobil dan Motor",
        "Nama Ketua": "Andi Pandaka",
        "Nama Sekretaris": "Rohani.Bsc",
        "Nama Bendahara": "Abdul Latif",
        "Nama Pengawas": " ",
        "Nama Manager": " ",
        "Jumlah Anggota Pria": "28",
        "Jumlah Anggota Wanita": "47",
        "Total Anggota": "75",
        "Total Manajer": "0",
        "Total Karyawan": "2",
        "Nomor Induk Koperasi (NIK)": "7316060080001",
        "Status NIK": "Sertifikat - Expired",
        "Tanggal Berlaku Sertifikat": "15/08/2021",
        "Status Grade": "A"
    },
    "7316090010001": {
        "Koperasi": "Koperasi Pertanian Padaidi",
        "Nomor Badan Hukum Pendirian": "77/BH/KDK.20.21/X/1999",
        "Tanggal Badan Hukum Pendirian": "26/10/1999",
        "Nomor Perubahan Anggaran Dasar (Terbaru)": " ",
        "Tanggal Perubahan Anggaran Dasar (Terbaru)": " ",
        "Tanggal RAT Terakhir": "15/06/2020",
        "Alamat": "Parandean,Poros Baroko Masalle",
        "Kelurahan / Desa": "Batu Kede",
        "Kecamatan": "Masalle",
        "Kabupaten": "Kab. Enrekang",
        "Provinsi": "Sulawesi Selatan",
        "Bentuk Koperasi": "Primer Kabupaten/Kota",
        "Jenis Koperasi": "Produsen",
        "Kelompok Koperasi": "Kop. Pertanian",
        "Sektor Usaha": "Perdagangan Besar dan Eceran - Rep Mobil dan Motor",
        "Nama Ketua": "Lasri",
        "Nama Sekretaris": "Laharis",
        "Nama Bendahara": "Irsan",
        "Nama Pengawas": " ",
        "Nama Manager": " ",
        "Jumlah Anggota Pria": "48",
        "Jumlah Anggota Wanita": "11",
        "Total Anggota": "59",
        "Total Manajer": "0",
        "Total Karyawan": "2",
        "Nomor Induk Koperasi (NIK)": "7316090010001",
        "Status NIK": "Sudah Bersertifikat",
        "Tanggal Berlaku Sertifikat": "26/10/2022",
        "Status Grade": "B"
    },
    "7316080040001": {
        "Koperasi": "Koperasi Tani Curio",
        "Nomor Badan Hukum Pendirian": "65/BH/KDK.2021/VII/1999",
        "Tanggal Badan Hukum Pendirian": "12/07/1999",
        "Nomor Perubahan Anggaran Dasar (Terbaru)": " ",
        "Tanggal Perubahan Anggaran Dasar (Terbaru)": " ",
        "Tanggal RAT Terakhir": "05/05/2021",
        "Alamat": "Curio Desa Curio Kecamatan Curio",
        "Kelurahan / Desa": "Desa Curio",
        "Kecamatan": "Curio",
        "Kabupaten": "Kab. Enrekang",
        "Provinsi": "Sulawesi Selatan",
        "Bentuk Koperasi": "Primer Kabupaten/Kota",
        "Jenis Koperasi": "Jasa",
        "Kelompok Koperasi": "Kop. Pertanian",
        "Sektor Usaha": "Jasa Keuangan dan Asuransi",
        "Nama Ketua": "Warman, SE",
        "Nama Sekretaris": "Suardi",
        "Nama Bendahara": "Erni Bare",
        "Nama Pengawas": " ",
        "Nama Manager": " ",
        "Jumlah Anggota Pria": "38",
        "Jumlah Anggota Wanita": "12",
        "Total Anggota": "50",
        "Total Manajer": "0",
        "Total Karyawan": "0",
        "Nomor Induk Koperasi (NIK)": "7316080040001",
        "Status NIK": "Sertifikat - Expired",
        "Tanggal Berlaku Sertifikat": "12/07/2020",
        "Status Grade": "A"
    },
    "7316120040006": {
        "Koperasi": "Koperasi Tani Benteng Alla",
        "Nomor Badan Hukum Pendirian": "93/KEP-BH/PPR/2.1/VIII/2001",
        "Tanggal Badan Hukum Pendirian": "31/08/2001",
        "Nomor Perubahan Anggaran Dasar (Terbaru)": " ",
        "Tanggal Perubahan Anggaran Dasar (Terbaru)": " ",
        "Tanggal RAT Terakhir": "27/05/2021",
        "Alamat": "Buntu Dama",
        "Kelurahan / Desa": "Desa Benteng Alla Utara",
        "Kecamatan": "Baroko",
        "Kabupaten": "Kab. Enrekang",
        "Provinsi": "Sulawesi Selatan",
        "Bentuk Koperasi": "Primer Kabupaten/Kota",
        "Jenis Koperasi": "Pemasaran",
        "Kelompok Koperasi": "Kop. Pertanian",
        "Sektor Usaha": "Pertanian, Kehutanan dan Perikanan",
        "Nama Ketua": "Edy Muchtar, S.Pd, M.AP",
        "Nama Sekretaris": "Ansyar A., S.Pi",
        "Nama Bendahara": "Lukman",
        "Nama Pengawas": " ",
        "Nama Manager": " ",
        "Jumlah Anggota Pria": "32",
        "Jumlah Anggota Wanita": "4",
        "Total Anggota": "36",
        "Total Manajer": "0",
        "Total Karyawan": "0",
        "Nomor Induk Koperasi (NIK)": "7316120040006",
        "Status NIK": "Sudah Bersertifikat",
        "Tanggal Berlaku Sertifikat": "31/08/2022",
        "Status Grade": "A"
    },
    "7316120060001": {
        "Koperasi": "Koperasi Tani Sipakaritutu",
        "Nomor Badan Hukum Pendirian": "86/BH/KDK.20.21/IX/2000",
        "Tanggal Badan Hukum Pendirian": "04/09/2000",
        "Nomor Perubahan Anggaran Dasar (Terbaru)": " ",
        "Tanggal Perubahan Anggaran Dasar (Terbaru)": " ",
        "Tanggal RAT Terakhir": "25/04/2021",
        "Alamat": "Bubunbia",
        "Kelurahan / Desa": "Desa Tongko",
        "Kecamatan": "Baroko",
        "Kabupaten": "Kab. Enrekang",
        "Provinsi": "Sulawesi Selatan",
        "Bentuk Koperasi": "Primer Kabupaten/Kota",
        "Jenis Koperasi": "Produsen",
        "Kelompok Koperasi": "Kop. Pertanian",
        "Sektor Usaha": "Pertanian, Kehutanan dan Perikanan",
        "Nama Ketua": "Muliati,sSE",
        "Nama Sekretaris": "Mustari",
        "Nama Bendahara": "Safri",
        "Nama Pengawas": " ",
        "Nama Manager": " ",
        "Jumlah Anggota Pria": "58",
        "Jumlah Anggota Wanita": "19",
        "Total Anggota": "77",
        "Total Manajer": "0",
        "Total Karyawan": "0",
        "Nomor Induk Koperasi (NIK)": "7316120060001",
        "Status NIK": "Sertifikat - Expired",
        "Tanggal Berlaku Sertifikat": "04/09/2020",
        "Status Grade": "A"
    },
    "7316080120009": {
        "Koperasi": "Koperasi Pegawai Negeri Setia Kawan SLTP 4 Alla",
        "Nomor Badan Hukum Pendirian": "114/KEP-BH/PPR/2.1/XII/2004",
        "Tanggal Badan Hukum Pendirian": "21/12/2004",
        "Nomor Perubahan Anggaran Dasar (Terbaru)": " ",
        "Tanggal Perubahan Anggaran Dasar (Terbaru)": " ",
        "Tanggal RAT Terakhir": "18/02/2021",
        "Alamat": "Kop SMP 4 Alla Kec.Curio",
        "Kelurahan / Desa": "Curio",
        "Kecamatan": "Curio",
        "Kabupaten": "Kab. Enrekang",
        "Provinsi": "Sulawesi Selatan",
        "Bentuk Koperasi": "Primer Kabupaten/Kota",
        "Jenis Koperasi": "Konsumen",
        "Kelompok Koperasi": "Kop. Pegawai Negeri (KPRI)",
        "Sektor Usaha": "Jasa Keuangan dan Asuransi",
        "Nama Ketua": "Sri Murwanto",
        "Nama Sekretaris": "Anton, S.Pd",
        "Nama Bendahara": "Mahir, S.Ag",
        "Nama Pengawas": " ",
        "Nama Manager": " ",
        "Jumlah Anggota Pria": "17",
        "Jumlah Anggota Wanita": "8",
        "Total Anggota": "25",
        "Total Manajer": "0",
        "Total Karyawan": "0",
        "Nomor Induk Koperasi (NIK)": "7316080120009",
        "Status NIK": "Belum Bersertifikat",
        "Tanggal Berlaku Sertifikat": " ",
        "Status Grade": "D"
    },
    "7316010010019": {
        "Koperasi": "Koperasi Remaja Reso Tamanggingi",
        "Nomor Badan Hukum Pendirian": "15/BH/KDK.2021/I/1999",
        "Tanggal Badan Hukum Pendirian": "30/01/1999",
        "Nomor Perubahan Anggaran Dasar (Terbaru)": " ",
        "Tanggal Perubahan Anggaran Dasar (Terbaru)": " ",
        "Tanggal RAT Terakhir": " ",
        "Alamat": "Limbuang Desa Palakka Kecamatan Maiwa",
        "Kelurahan / Desa": "Desa Palakka",
        "Kecamatan": "Maiwa",
        "Kabupaten": "Kab. Enrekang",
        "Provinsi": "Sulawesi Selatan",
        "Bentuk Koperasi": "Primer Kabupaten/Kota",
        "Jenis Koperasi": "Konsumen",
        "Kelompok Koperasi": "Kop. Pemuda",
        "Sektor Usaha": "Jasa Keuangan dan Asuransi",
        "Nama Ketua": " ",
        "Nama Sekretaris": " ",
        "Nama Bendahara": " ",
        "Nama Pengawas": " ",
        "Nama Manager": " ",
        "Jumlah Anggota Pria": "0",
        "Jumlah Anggota Wanita": "0",
        "Total Anggota": "0",
        "Total Manajer": "0",
        "Total Karyawan": "0",
        "Nomor Induk Koperasi (NIK)": "7316010010019",
        "Status NIK": "Belum Bersertifikat",
        "Tanggal Berlaku Sertifikat": " ",
        "Status Grade": "D"
    },
    "7316100010001": {
        "Koperasi": "Koperasi Pertanian Batu Ciak",
        "Nomor Badan Hukum Pendirian": "73/BH/KDK.20.21/IX/1999",
        "Tanggal Badan Hukum Pendirian": "24/09/1999",
        "Nomor Perubahan Anggaran Dasar (Terbaru)": " ",
        "Tanggal Perubahan Anggaran Dasar (Terbaru)": " ",
        "Tanggal RAT Terakhir": " ",
        "Alamat": "Desa Panatakan Bungin",
        "Kelurahan / Desa": "Desa Panatakan",
        "Kecamatan": "Bungin",
        "Kabupaten": "Kab. Enrekang",
        "Provinsi": "Sulawesi Selatan",
        "Bentuk Koperasi": "Primer Kabupaten/Kota",
        "Jenis Koperasi": "Produsen",
        "Kelompok Koperasi": "Kop. Pertanian",
        "Sektor Usaha": "Pertanian, Kehutanan dan Perikanan",
        "Nama Ketua": " ",
        "Nama Sekretaris": " ",
        "Nama Bendahara": " ",
        "Nama Pengawas": " ",
        "Nama Manager": " ",
        "Jumlah Anggota Pria": "0",
        "Jumlah Anggota Wanita": "0",
        "Total Anggota": "0",
        "Total Manajer": "0",
        "Total Karyawan": "0",
        "Nomor Induk Koperasi (NIK)": "7316100010001",
        "Status NIK": "Belum Bersertifikat",
        "Tanggal Berlaku Sertifikat": " ",
        "Status Grade": "D"
    },
    "7316100010002": {
        "Koperasi": "Koperasi Wai Tuo",
        "Nomor Badan Hukum Pendirian": "146/BH/XXIV.4/VIII/2011",
        "Tanggal Badan Hukum Pendirian": "18/08/2011",
        "Nomor Perubahan Anggaran Dasar (Terbaru)": " ",
        "Tanggal Perubahan Anggaran Dasar (Terbaru)": " ",
        "Tanggal RAT Terakhir": " ",
        "Alamat": "Betteng Tallang Rilau Kecamatan Bungin",
        "Kelurahan / Desa": "Desa Tallang Rilau",
        "Kecamatan": "Bungin",
        "Kabupaten": "Kab. Enrekang",
        "Provinsi": "Sulawesi Selatan",
        "Bentuk Koperasi": "Primer Kabupaten/Kota",
        "Jenis Koperasi": "Konsumen",
        "Kelompok Koperasi": "Kop. Lainnya",
        "Sektor Usaha": "Jasa Lainnya",
        "Nama Ketua": " ",
        "Nama Sekretaris": " ",
        "Nama Bendahara": " ",
        "Nama Pengawas": " ",
        "Nama Manager": " ",
        "Jumlah Anggota Pria": "0",
        "Jumlah Anggota Wanita": "0",
        "Total Anggota": "0",
        "Total Manajer": "0",
        "Total Karyawan": "0",
        "Nomor Induk Koperasi (NIK)": "7316100010002",
        "Status NIK": "Belum Bersertifikat",
        "Tanggal Berlaku Sertifikat": " ",
        "Status Grade": "D"
    },
    "7316110020020": {
        "Koperasi": "Koperasi Pertanian Usaha Bersama Way Lolong",
        "Nomor Badan Hukum Pendirian": "19/BH/KDK.2021/II/1999",
        "Tanggal Badan Hukum Pendirian": "13/02/1999",
        "Nomor Perubahan Anggaran Dasar (Terbaru)": " ",
        "Tanggal Perubahan Anggaran Dasar (Terbaru)": " ",
        "Tanggal RAT Terakhir": " ",
        "Alamat": "Pasongken",
        "Kelurahan / Desa": "Desa Buntu Mondong",
        "Kecamatan": "Buntu Batu",
        "Kabupaten": "Kab. Enrekang",
        "Provinsi": "Sulawesi Selatan",
        "Bentuk Koperasi": "Primer Kabupaten/Kota",
        "Jenis Koperasi": "Produsen",
        "Kelompok Koperasi": "Kop. Pertanian",
        "Sektor Usaha": "Pertanian, Kehutanan dan Perikanan",
        "Nama Ketua": " ",
        "Nama Sekretaris": " ",
        "Nama Bendahara": " ",
        "Nama Pengawas": " ",
        "Nama Manager": " ",
        "Jumlah Anggota Pria": "0",
        "Jumlah Anggota Wanita": "0",
        "Total Anggota": "0",
        "Total Manajer": "0",
        "Total Karyawan": "0",
        "Nomor Induk Koperasi (NIK)": "7316110020020",
        "Status NIK": "Belum Bersertifikat",
        "Tanggal Berlaku Sertifikat": " ",
        "Status Grade": "D"
    },
    "7316070010006": {
        "Koperasi": "Koperasi Pegawai Republik Indonesia Dewantara SLTP 2 Anggeraja",
        "Nomor Badan Hukum Pendirian": "07/BH/KDK.20.21/X/1998",
        "Tanggal Badan Hukum Pendirian": "28/10/1998",
        "Nomor Perubahan Anggaran Dasar (Terbaru)": " ",
        "Tanggal Perubahan Anggaran Dasar (Terbaru)": " ",
        "Tanggal RAT Terakhir": "06/01/2021",
        "Alamat": "Jl. Pendidikan No. 9 Malua",
        "Kelurahan / Desa": "Malua",
        "Kecamatan": "Malua",
        "Kabupaten": "Kab. Enrekang",
        "Provinsi": "Sulawesi Selatan",
        "Bentuk Koperasi": "Primer Kabupaten/Kota",
        "Jenis Koperasi": "Konsumen",
        "Kelompok Koperasi": "Kop. Pegawai Negeri (KPRI)",
        "Sektor Usaha": "Jasa Keuangan dan Asuransi",
        "Nama Ketua": "Supardi Harjo, S.Pd",
        "Nama Sekretaris": "Arsduddin Addas, S.Pd, M.Pd",
        "Nama Bendahara": "Badaria Desa, S.Pd",
        "Nama Pengawas": " ",
        "Nama Manager": " ",
        "Jumlah Anggota Pria": "16",
        "Jumlah Anggota Wanita": "17",
        "Total Anggota": "33",
        "Total Manajer": "0",
        "Total Karyawan": "0",
        "Nomor Induk Koperasi (NIK)": "7316070010006",
        "Status NIK": "Belum Bersertifikat",
        "Tanggal Berlaku Sertifikat": " ",
        "Status Grade": "D"
    },
    "7316070060008": {
        "Koperasi": "Koperasi Wanita Buntu Duri",
        "Nomor Badan Hukum Pendirian": "147/BH/XXIV.4/XI/2011",
        "Tanggal Badan Hukum Pendirian": "09/11/2011",
        "Nomor Perubahan Anggaran Dasar (Terbaru)": " ",
        "Tanggal Perubahan Anggaran Dasar (Terbaru)": " ",
        "Tanggal RAT Terakhir": "15/04/2018",
        "Alamat": "Jl. DR. Syukur Abdullah",
        "Kelurahan / Desa": "Kelurahan Malua",
        "Kecamatan": "Malua",
        "Kabupaten": "Kab. Enrekang",
        "Provinsi": "Sulawesi Selatan",
        "Bentuk Koperasi": "Primer Kabupaten/Kota",
        "Jenis Koperasi": "Konsumen",
        "Kelompok Koperasi": "Kop. Wanita",
        "Sektor Usaha": "Jasa Keuangan dan Asuransi",
        "Nama Ketua": " ",
        "Nama Sekretaris": " ",
        "Nama Bendahara": " ",
        "Nama Pengawas": " ",
        "Nama Manager": " ",
        "Jumlah Anggota Pria": "0",
        "Jumlah Anggota Wanita": "31",
        "Total Anggota": "31",
        "Total Manajer": "0",
        "Total Karyawan": "0",
        "Nomor Induk Koperasi (NIK)": "7316070060008",
        "Status NIK": "Belum Bersertifikat",
        "Tanggal Berlaku Sertifikat": " ",
        "Status Grade": "D"
    },
    "7316080010001": {
        "Koperasi": "Koperasi Unit Desa Rante Limbong",
        "Nomor Badan Hukum Pendirian": "5184/BH/IV",
        "Tanggal Badan Hukum Pendirian": "20/06/1996",
        "Nomor Perubahan Anggaran Dasar (Terbaru)": "116/PAD/KWK.20/VI/1996",
        "Tanggal Perubahan Anggaran Dasar (Terbaru)": "20/06/1996",
        "Tanggal RAT Terakhir": "12/02/2018",
        "Alamat": "Rante Limbong, Desa Buntu Barana",
        "Kelurahan / Desa": "Buntu Barana",
        "Kecamatan": "Curio",
        "Kabupaten": "Kab. Enrekang",
        "Provinsi": "Sulawesi Selatan",
        "Bentuk Koperasi": "Primer Kabupaten/Kota",
        "Jenis Koperasi": "Produsen",
        "Kelompok Koperasi": "KUD",
        "Sektor Usaha": "Jasa Keuangan dan Asuransi",
        "Nama Ketua": "Mustawakkal",
        "Nama Sekretaris": "Ir. Awaluddin, T",
        "Nama Bendahara": "Takdir Arifin",
        "Nama Pengawas": " ",
        "Nama Manager": " ",
        "Jumlah Anggota Pria": "53",
        "Jumlah Anggota Wanita": "27",
        "Total Anggota": "80",
        "Total Manajer": "0",
        "Total Karyawan": "3",
        "Nomor Induk Koperasi (NIK)": "7316080010001",
        "Status NIK": "Belum Bersertifikat",
        "Tanggal Berlaku Sertifikat": " ",
        "Status Grade": "D"
    },
    "7316060020004": {
        "Koperasi": "KOPERASI PRODUSEN PETERNAK SAPI PERAH CENDANA",
        "Nomor Badan Hukum Pendirian": "AHU-0008265.AH.01.26.TAHUN 2021",
        "Tanggal Badan Hukum Pendirian": "02/02/2021",
        "Nomor Perubahan Anggaran Dasar (Terbaru)": " ",
        "Tanggal Perubahan Anggaran Dasar (Terbaru)": " ",
        "Tanggal RAT Terakhir": " ",
        "Alamat": "Baba",
        "Kelurahan / Desa": "Cendana",
        "Kecamatan": "Cendana",
        "Kabupaten": "Kab. Enrekang",
        "Provinsi": "Sulawesi Selatan",
        "Bentuk Koperasi": "Primer Kabupaten/Kota",
        "Jenis Koperasi": "Produsen",
        "Kelompok Koperasi": "Kop. Lainnya",
        "Sektor Usaha": "Jasa Lainnya",
        "Nama Ketua": "SABRAN",
        "Nama Sekretaris": "MUHAMMAD ZULFIKAR",
        "Nama Bendahara": "AMILUDDIN",
        "Nama Pengawas": " ",
        "Nama Manager": " ",
        "Jumlah Anggota Pria": "0",
        "Jumlah Anggota Wanita": "0",
        "Total Anggota": "0",
        "Total Manajer": "0",
        "Total Karyawan": "0",
        "Nomor Induk Koperasi (NIK)": "7316060020004",
        "Status NIK": "Belum Bersertifikat",
        "Tanggal Berlaku Sertifikat": " ",
        "Status Grade": "D"
    },
    "7316040160027": {
        "Koperasi": "Koperasi Pegawai Negeri Sekolaha Menengah Umum Negeri 229 Cakke",
        "Nomor Badan Hukum Pendirian": "5259/BH/IV",
        "Tanggal Badan Hukum Pendirian": "02/05/1992",
        "Nomor Perubahan Anggaran Dasar (Terbaru)": "507/PAD/KWK.20/VII/1997",
        "Tanggal Perubahan Anggaran Dasar (Terbaru)": "14/07/1997",
        "Tanggal RAT Terakhir": "21/02/2018",
        "Alamat": "Cakke Kelurahan Tanete",
        "Kelurahan / Desa": "Kelurahan Tanete",
        "Kecamatan": "Anggeraja",
        "Kabupaten": "Kab. Enrekang",
        "Provinsi": "Sulawesi Selatan",
        "Bentuk Koperasi": "Primer Kabupaten/Kota",
        "Jenis Koperasi": "Konsumen",
        "Kelompok Koperasi": "Kop. Pegawai Negeri (KPRI)",
        "Sektor Usaha": "Jasa Keuangan dan Asuransi",
        "Nama Ketua": "Khairul, S.Pd",
        "Nama Sekretaris": "Dra. Bunga",
        "Nama Bendahara": "Rahmi, S.Pd",
        "Nama Pengawas": " ",
        "Nama Manager": " ",
        "Jumlah Anggota Pria": "27",
        "Jumlah Anggota Wanita": "16",
        "Total Anggota": "43",
        "Total Manajer": "0",
        "Total Karyawan": "1",
        "Nomor Induk Koperasi (NIK)": "7316040160027",
        "Status NIK": "Belum Bersertifikat",
        "Tanggal Berlaku Sertifikat": " ",
        "Status Grade": "D"
    },
    "7316050010019": {
        "Koperasi": "Koperasi Simpan Pinjam Mekar Kambiolangi",
        "Nomor Badan Hukum Pendirian": "177/KEP-BH/PPD/IV/2005",
        "Tanggal Badan Hukum Pendirian": "24/03/2005",
        "Nomor Perubahan Anggaran Dasar (Terbaru)": " ",
        "Tanggal Perubahan Anggaran Dasar (Terbaru)": " ",
        "Tanggal RAT Terakhir": "16/03/2018",
        "Alamat": "Belajen Kelurahan Kambiolangi",
        "Kelurahan / Desa": "Kambiolangi",
        "Kecamatan": "Alla",
        "Kabupaten": "Kab. Enrekang",
        "Provinsi": "Sulawesi Selatan",
        "Bentuk Koperasi": "Primer Kabupaten/Kota",
        "Jenis Koperasi": "Simpan Pinjam",
        "Kelompok Koperasi": "Kop. Simpan Pinjam",
        "Sektor Usaha": "Jasa Keuangan dan Asuransi",
        "Nama Ketua": " ",
        "Nama Sekretaris": " ",
        "Nama Bendahara": " ",
        "Nama Pengawas": " ",
        "Nama Manager": " ",
        "Jumlah Anggota Pria": "133",
        "Jumlah Anggota Wanita": "109",
        "Total Anggota": "242",
        "Total Manajer": "0",
        "Total Karyawan": "4",
        "Nomor Induk Koperasi (NIK)": "7316050010019",
        "Status NIK": "Belum Bersertifikat",
        "Tanggal Berlaku Sertifikat": " ",
        "Status Grade": "D"
    },
    "7316040050003": {
        "Koperasi": "Koperasi Unit Desa Bambapuang",
        "Nomor Badan Hukum Pendirian": "3789/BH/IV",
        "Tanggal Badan Hukum Pendirian": "15/08/1983",
        "Nomor Perubahan Anggaran Dasar (Terbaru)": " ",
        "Tanggal Perubahan Anggaran Dasar (Terbaru)": " ",
        "Tanggal RAT Terakhir": " ",
        "Alamat": "Pasar Cakke Kelurahan Lakawan",
        "Kelurahan / Desa": "Kelurahan Lakawan",
        "Kecamatan": "Anggeraja",
        "Kabupaten": "Kab. Enrekang",
        "Provinsi": "Sulawesi Selatan",
        "Bentuk Koperasi": "Primer Kabupaten/Kota",
        "Jenis Koperasi": "Produsen",
        "Kelompok Koperasi": "Kop. Lainnya",
        "Sektor Usaha": "Jasa Lainnya",
        "Nama Ketua": " ",
        "Nama Sekretaris": " ",
        "Nama Bendahara": " ",
        "Nama Pengawas": " ",
        "Nama Manager": " ",
        "Jumlah Anggota Pria": "0",
        "Jumlah Anggota Wanita": "0",
        "Total Anggota": "0",
        "Total Manajer": "0",
        "Total Karyawan": "0",
        "Nomor Induk Koperasi (NIK)": "7316040050003",
        "Status NIK": "Belum Bersertifikat",
        "Tanggal Berlaku Sertifikat": " ",
        "Status Grade": "D"
    },
    "7316040030001": {
        "Koperasi": "Koperasi Pemuda Tani Lumbaja",
        "Nomor Badan Hukum Pendirian": "150/BH/XXIV.4/III/2012",
        "Tanggal Badan Hukum Pendirian": "29/03/2012",
        "Nomor Perubahan Anggaran Dasar (Terbaru)": " ",
        "Tanggal Perubahan Anggaran Dasar (Terbaru)": " ",
        "Tanggal RAT Terakhir": " ",
        "Alamat": "Batu Noni Desa Batu Noni",
        "Kelurahan / Desa": "Desa Batu Noni",
        "Kecamatan": "Anggeraja",
        "Kabupaten": "Kab. Enrekang",
        "Provinsi": "Sulawesi Selatan",
        "Bentuk Koperasi": "Primer Kabupaten/Kota",
        "Jenis Koperasi": "Produsen",
        "Kelompok Koperasi": "Kop. Lainnya",
        "Sektor Usaha": "Jasa Lainnya",
        "Nama Ketua": " ",
        "Nama Sekretaris": " ",
        "Nama Bendahara": " ",
        "Nama Pengawas": " ",
        "Nama Manager": " ",
        "Jumlah Anggota Pria": "0",
        "Jumlah Anggota Wanita": "0",
        "Total Anggota": "0",
        "Total Manajer": "0",
        "Total Karyawan": "0",
        "Nomor Induk Koperasi (NIK)": "7316040030001",
        "Status NIK": "Belum Bersertifikat",
        "Tanggal Berlaku Sertifikat": " ",
        "Status Grade": "D"
    },
    "7316020120002": {
        "Koperasi": "KOPERASI PRODUSEN ENREKANG TIMUR KASITURUTAN",
        "Nomor Badan Hukum Pendirian": "AHU-0001716.AH.01.26.TAHUN 2020",
        "Tanggal Badan Hukum Pendirian": "17/01/2020",
        "Nomor Perubahan Anggaran Dasar (Terbaru)": " ",
        "Tanggal Perubahan Anggaran Dasar (Terbaru)": " ",
        "Tanggal RAT Terakhir": "02/03/2021",
        "Alamat": "Ranga Baru",
        "Kelurahan / Desa": "Ranga",
        "Kecamatan": "Enrekang",
        "Kabupaten": "Kab. Enrekang",
        "Provinsi": "Sulawesi Selatan",
        "Bentuk Koperasi": "Primer Kabupaten/Kota",
        "Jenis Koperasi": "Produsen",
        "Kelompok Koperasi": "Kop. Lainnya",
        "Sektor Usaha": "Jasa Lainnya",
        "Nama Ketua": "Mustarim Latif",
        "Nama Sekretaris": "Saidi",
        "Nama Bendahara": "Muhammad Syukur",
        "Nama Pengawas": " ",
        "Nama Manager": " ",
        "Jumlah Anggota Pria": "22",
        "Jumlah Anggota Wanita": "6",
        "Total Anggota": "28",
        "Total Manajer": "0",
        "Total Karyawan": "0",
        "Nomor Induk Koperasi (NIK)": "7316020120002",
        "Status NIK": "Belum Bersertifikat",
        "Tanggal Berlaku Sertifikat": " ",
        "Status Grade": "D"
    },
    "7316020110001": {
        "Koperasi": "Koperasi Pegawai Negeri Bakti Husada Kandep Kesehatan Kab Enrekang",
        "Nomor Badan Hukum Pendirian": "3567a/BH/IV",
        "Tanggal Badan Hukum Pendirian": "11/04/1972",
        "Nomor Perubahan Anggaran Dasar (Terbaru)": "704/PAD/KWK.20/XII/1996",
        "Tanggal Perubahan Anggaran Dasar (Terbaru)": "16/12/1996",
        "Tanggal RAT Terakhir": "20/06/2017",
        "Alamat": "Jl. Sultan Hasanuddin No. 56",
        "Kelurahan / Desa": "Puserren",
        "Kecamatan": "Enrekang",
        "Kabupaten": "Kab. Enrekang",
        "Provinsi": "Sulawesi Selatan",
        "Bentuk Koperasi": "Primer Kabupaten/Kota",
        "Jenis Koperasi": "Jasa",
        "Kelompok Koperasi": "Kop. Pegawai Negeri (KPRI)",
        "Sektor Usaha": "Jasa Keuangan dan Asuransi",
        "Nama Ketua": "Suharny , SKM",
        "Nama Sekretaris": " ",
        "Nama Bendahara": " ",
        "Nama Pengawas": " ",
        "Nama Manager": " ",
        "Jumlah Anggota Pria": "170",
        "Jumlah Anggota Wanita": "31",
        "Total Anggota": "201",
        "Total Manajer": "0",
        "Total Karyawan": "0",
        "Nomor Induk Koperasi (NIK)": "7316020110001",
        "Status NIK": "Belum Bersertifikat",
        "Tanggal Berlaku Sertifikat": " ",
        "Status Grade": "D"
    },
    "7316020200019": {
        "Koperasi": "KOPERASI KONSUMEN KORPRI KABUPATEN ENREKANG",
        "Nomor Badan Hukum Pendirian": "AHU-0012826.AH.01.26.TAHUN 2021",
        "Tanggal Badan Hukum Pendirian": "18/10/2021",
        "Nomor Perubahan Anggaran Dasar (Terbaru)": " ",
        "Tanggal Perubahan Anggaran Dasar (Terbaru)": " ",
        "Tanggal RAT Terakhir": " ",
        "Alamat": "Sekretariat Korpri Kabupaten Enrekang/Gedung BKPSDM Lantai I Jalan Jenderal Sudirman No. 13 Batili Enrekang",
        "Kelurahan / Desa": "Galonta",
        "Kecamatan": "Enrekang",
        "Kabupaten": "Kab. Enrekang",
        "Provinsi": "Sulawesi Selatan",
        "Bentuk Koperasi": "Primer Kabupaten/Kota",
        "Jenis Koperasi": "Konsumen",
        "Kelompok Koperasi": "Kop. Lainnya",
        "Sektor Usaha": "Jasa Lainnya",
        "Nama Ketua": "SYAMSUDDIN, S.PT., M.SI",
        "Nama Sekretaris": "AMIRULLAH, SE., M.AP",
        "Nama Bendahara": "ROSNANI, S.A.P.",
        "Nama Pengawas": " ",
        "Nama Manager": " ",
        "Jumlah Anggota Pria": "0",
        "Jumlah Anggota Wanita": "0",
        "Total Anggota": "0",
        "Total Manajer": "0",
        "Total Karyawan": "0",
        "Nomor Induk Koperasi (NIK)": "7316020200019",
        "Status NIK": "Belum Bersertifikat",
        "Tanggal Berlaku Sertifikat": " ",
        "Status Grade": "D"
    },
    "7316030010002": {
        "Koperasi": "Koperasi Unit Desa Tirowalie",
        "Nomor Badan Hukum Pendirian": "4168/BH/IV",
        "Tanggal Badan Hukum Pendirian": "06/07/1981",
        "Nomor Perubahan Anggaran Dasar (Terbaru)": " ",
        "Tanggal Perubahan Anggaran Dasar (Terbaru)": " ",
        "Tanggal RAT Terakhir": "11/10/2021",
        "Alamat": "Pasar Sentral Baraka",
        "Kelurahan / Desa": "Baraka",
        "Kecamatan": "Baraka",
        "Kabupaten": "Kab. Enrekang",
        "Provinsi": "Sulawesi Selatan",
        "Bentuk Koperasi": "Primer Kabupaten/Kota",
        "Jenis Koperasi": "Produsen",
        "Kelompok Koperasi": "KUD",
        "Sektor Usaha": "Pertanian, Kehutanan dan Perikanan",
        "Nama Ketua": "Simen",
        "Nama Sekretaris": "Syarifuddin",
        "Nama Bendahara": "Alimuddin",
        "Nama Pengawas": " ",
        "Nama Manager": " ",
        "Jumlah Anggota Pria": "195",
        "Jumlah Anggota Wanita": "115",
        "Total Anggota": "310",
        "Total Manajer": "0",
        "Total Karyawan": "3",
        "Nomor Induk Koperasi (NIK)": "7316030010002",
        "Status NIK": "Belum Bersertifikat",
        "Tanggal Berlaku Sertifikat": " ",
        "Status Grade": "D"
    },
    "7316030010009": {
        "Koperasi": "Koperasi Wanita Sejahtera Aisiyah",
        "Nomor Badan Hukum Pendirian": "51/BH/KDK",
        "Tanggal Badan Hukum Pendirian": "11/05/1999",
        "Nomor Perubahan Anggaran Dasar (Terbaru)": " ",
        "Tanggal Perubahan Anggaran Dasar (Terbaru)": " ",
        "Tanggal RAT Terakhir": " ",
        "Alamat": "Baraka Kelurahan Baraka",
        "Kelurahan / Desa": "Kelurahan Baraka",
        "Kecamatan": "Baraka",
        "Kabupaten": "Kab. Enrekang",
        "Provinsi": "Sulawesi Selatan",
        "Bentuk Koperasi": "Primer Kabupaten/Kota",
        "Jenis Koperasi": "Konsumen",
        "Kelompok Koperasi": "Kop. Wanita",
        "Sektor Usaha": "Jasa Lainnya",
        "Nama Ketua": " ",
        "Nama Sekretaris": " ",
        "Nama Bendahara": " ",
        "Nama Pengawas": " ",
        "Nama Manager": " ",
        "Jumlah Anggota Pria": "0",
        "Jumlah Anggota Wanita": "0",
        "Total Anggota": "0",
        "Total Manajer": "0",
        "Total Karyawan": "0",
        "Nomor Induk Koperasi (NIK)": "7316030010009",
        "Status NIK": "Belum Bersertifikat",
        "Tanggal Berlaku Sertifikat": " ",
        "Status Grade": "D"
    },
    "7316030040014": {
        "Koperasi": "Koperasi Pegawai Negeri Sekolah Menengah Pertama Negeri Baraka",
        "Nomor Badan Hukum Pendirian": "4178/BH/IV",
        "Tanggal Badan Hukum Pendirian": "17/07/1987",
        "Nomor Perubahan Anggaran Dasar (Terbaru)": "917/PAD/KWK.20/X/1997",
        "Tanggal Perubahan Anggaran Dasar (Terbaru)": " ",
        "Tanggal RAT Terakhir": "24/02/2021",
        "Alamat": "Baraka Kelurahan Baraka",
        "Kelurahan / Desa": "Kelurahan Baraka",
        "Kecamatan": "Baraka",
        "Kabupaten": "Kab. Enrekang",
        "Provinsi": "Sulawesi Selatan",
        "Bentuk Koperasi": "Primer Kabupaten/Kota",
        "Jenis Koperasi": "Konsumen",
        "Kelompok Koperasi": "Kop. Pegawai Negeri (KPRI)",
        "Sektor Usaha": "Jasa Keuangan dan Asuransi",
        "Nama Ketua": "Drs. Darwis",
        "Nama Sekretaris": "Dra. Nurjannah",
        "Nama Bendahara": "Naki, S.Pd",
        "Nama Pengawas": " ",
        "Nama Manager": " ",
        "Jumlah Anggota Pria": "14",
        "Jumlah Anggota Wanita": "26",
        "Total Anggota": "40",
        "Total Manajer": "0",
        "Total Karyawan": "0",
        "Nomor Induk Koperasi (NIK)": "7316030040014",
        "Status NIK": "Belum Bersertifikat",
        "Tanggal Berlaku Sertifikat": " ",
        "Status Grade": "D"
    },
    "7316030040024": {
        "Koperasi": "Koperasi Guru-Guru Baraka",
        "Nomor Badan Hukum Pendirian": "5099/BH/IV",
        "Tanggal Badan Hukum Pendirian": "30/08/1990",
        "Nomor Perubahan Anggaran Dasar (Terbaru)": " ",
        "Tanggal Perubahan Anggaran Dasar (Terbaru)": " ",
        "Tanggal RAT Terakhir": "23/04/2018",
        "Alamat": "Baraka Kelurahan Baraka",
        "Kelurahan / Desa": "Kelurahan Baraka",
        "Kecamatan": "Baraka",
        "Kabupaten": "Kab. Enrekang",
        "Provinsi": "Sulawesi Selatan",
        "Bentuk Koperasi": "Primer Kabupaten/Kota",
        "Jenis Koperasi": "Konsumen",
        "Kelompok Koperasi": "Kop. Pegawai Negeri (KPRI)",
        "Sektor Usaha": "Jasa Keuangan dan Asuransi",
        "Nama Ketua": " ",
        "Nama Sekretaris": " ",
        "Nama Bendahara": " ",
        "Nama Pengawas": " ",
        "Nama Manager": " ",
        "Jumlah Anggota Pria": "90",
        "Jumlah Anggota Wanita": "80",
        "Total Anggota": "170",
        "Total Manajer": "0",
        "Total Karyawan": "3",
        "Nomor Induk Koperasi (NIK)": "7316030040024",
        "Status NIK": "Belum Bersertifikat",
        "Tanggal Berlaku Sertifikat": " ",
        "Status Grade": "D"
    },
    "7316040010022": {
        "Koperasi": "Koperasi Massempo Dalle",
        "Nomor Badan Hukum Pendirian": "142/BH/XXIV.4",
        "Tanggal Badan Hukum Pendirian": "22/11/2010",
        "Nomor Perubahan Anggaran Dasar (Terbaru)": " ",
        "Tanggal Perubahan Anggaran Dasar (Terbaru)": " ",
        "Tanggal RAT Terakhir": " ",
        "Alamat": "Jl. Pendidikan No. 45 Kelurahan Tanete",
        "Kelurahan / Desa": "Kelurahan Tanete",
        "Kecamatan": "Anggeraja",
        "Kabupaten": "Kab. Enrekang",
        "Provinsi": "Sulawesi Selatan",
        "Bentuk Koperasi": "Primer Kabupaten/Kota",
        "Jenis Koperasi": "Konsumen",
        "Kelompok Koperasi": "Kop. Lainnya",
        "Sektor Usaha": "Jasa Lainnya",
        "Nama Ketua": " ",
        "Nama Sekretaris": " ",
        "Nama Bendahara": " ",
        "Nama Pengawas": " ",
        "Nama Manager": " ",
        "Jumlah Anggota Pria": "0",
        "Jumlah Anggota Wanita": "0",
        "Total Anggota": "0",
        "Total Manajer": "0",
        "Total Karyawan": "0",
        "Nomor Induk Koperasi (NIK)": "7316040010022",
        "Status NIK": "Belum Bersertifikat",
        "Tanggal Berlaku Sertifikat": " ",
        "Status Grade": "D"
    },
    "7316020050008": {
        "Koperasi": "Koperasi Simpan Pinjam Bhakti Huria",
        "Nomor Badan Hukum Pendirian": "14/BH/DKUKM",
        "Tanggal Badan Hukum Pendirian": "23/12/2003",
        "Nomor Perubahan Anggaran Dasar (Terbaru)": " ",
        "Tanggal Perubahan Anggaran Dasar (Terbaru)": " ",
        "Tanggal RAT Terakhir": " ",
        "Alamat": "Jl. Industri Enrekang",
        "Kelurahan / Desa": "Kelurahan Juppandang",
        "Kecamatan": "Enrekang",
        "Kabupaten": "Kab. Enrekang",
        "Provinsi": "Sulawesi Selatan",
        "Bentuk Koperasi": "Primer Kabupaten/Kota",
        "Jenis Koperasi": "Produsen",
        "Kelompok Koperasi": "Kop. Lainnya",
        "Sektor Usaha": "Jasa Lainnya",
        "Nama Ketua": " ",
        "Nama Sekretaris": " ",
        "Nama Bendahara": " ",
        "Nama Pengawas": " ",
        "Nama Manager": " ",
        "Jumlah Anggota Pria": "0",
        "Jumlah Anggota Wanita": "0",
        "Total Anggota": "0",
        "Total Manajer": "0",
        "Total Karyawan": "0",
        "Nomor Induk Koperasi (NIK)": "7316020050008",
        "Status NIK": "Belum Bersertifikat",
        "Tanggal Berlaku Sertifikat": " ",
        "Status Grade": "D"
    },
    "7316020050009": {
        "Koperasi": "Koperasi Simpan Pinjam Berkat",
        "Nomor Badan Hukum Pendirian": "06/BH/PAD/KWK.20/IV/1996",
        "Tanggal Badan Hukum Pendirian": "22/04/1996",
        "Nomor Perubahan Anggaran Dasar (Terbaru)": " ",
        "Tanggal Perubahan Anggaran Dasar (Terbaru)": " ",
        "Tanggal RAT Terakhir": " ",
        "Alamat": "Jl. Indo Rangan Enrekang",
        "Kelurahan / Desa": "Kelurahan Juppandang",
        "Kecamatan": "Enrekang",
        "Kabupaten": "Kab. Enrekang",
        "Provinsi": "Sulawesi Selatan",
        "Bentuk Koperasi": "Primer Kabupaten/Kota",
        "Jenis Koperasi": "Produsen",
        "Kelompok Koperasi": "Kop. Lainnya",
        "Sektor Usaha": "Jasa Lainnya",
        "Nama Ketua": " ",
        "Nama Sekretaris": " ",
        "Nama Bendahara": " ",
        "Nama Pengawas": " ",
        "Nama Manager": " ",
        "Jumlah Anggota Pria": "0",
        "Jumlah Anggota Wanita": "0",
        "Total Anggota": "0",
        "Total Manajer": "0",
        "Total Karyawan": "0",
        "Nomor Induk Koperasi (NIK)": "7316020050009",
        "Status NIK": "Belum Bersertifikat",
        "Tanggal Berlaku Sertifikat": " ",
        "Status Grade": "D"
    },
    "7316020010001": {
        "Koperasi": "Koperasi Unit Desa Tokkonan",
        "Nomor Badan Hukum Pendirian": "4945/BHIV",
        "Tanggal Badan Hukum Pendirian": "17/04/1989",
        "Nomor Perubahan Anggaran Dasar (Terbaru)": " ",
        "Tanggal Perubahan Anggaran Dasar (Terbaru)": " ",
        "Tanggal RAT Terakhir": "18/05/2021",
        "Alamat": "Jl. Kemakmuran No.38 Enrkang",
        "Kelurahan / Desa": "Juppandang",
        "Kecamatan": "Enrekang",
        "Kabupaten": "Kab. Enrekang",
        "Provinsi": "Sulawesi Selatan",
        "Bentuk Koperasi": "Primer Kabupaten/Kota",
        "Jenis Koperasi": "Jasa",
        "Kelompok Koperasi": "KUD",
        "Sektor Usaha": "Jasa Lainnya",
        "Nama Ketua": "Sida Lajumbung",
        "Nama Sekretaris": "Ely Kamaya",
        "Nama Bendahara": "Bambang Djamma,S.Kom,M.Si",
        "Nama Pengawas": " ",
        "Nama Manager": " ",
        "Jumlah Anggota Pria": "27",
        "Jumlah Anggota Wanita": "14",
        "Total Anggota": "41",
        "Total Manajer": "0",
        "Total Karyawan": "0",
        "Nomor Induk Koperasi (NIK)": "7316020010001",
        "Status NIK": "Belum Bersertifikat",
        "Tanggal Berlaku Sertifikat": " ",
        "Status Grade": "D"
    },
    "7316020010006": {
        "Koperasi": "Koperasi Pertanian Tiro Padang",
        "Nomor Badan Hukum Pendirian": "100/KEP-BH/PPD/2.1/I/2004",
        "Tanggal Badan Hukum Pendirian": "26/01/2004",
        "Nomor Perubahan Anggaran Dasar (Terbaru)": " ",
        "Tanggal Perubahan Anggaran Dasar (Terbaru)": " ",
        "Tanggal RAT Terakhir": "30/11/2018",
        "Alamat": "Lapin Tobalu",
        "Kelurahan / Desa": "Kelurahan Tobalu",
        "Kecamatan": "Enrekang",
        "Kabupaten": "Kab. Enrekang",
        "Provinsi": "Sulawesi Selatan",
        "Bentuk Koperasi": "Primer Kabupaten/Kota",
        "Jenis Koperasi": "Produsen",
        "Kelompok Koperasi": "Kop. Pertanian",
        "Sektor Usaha": "Pertanian, Kehutanan dan Perikanan",
        "Nama Ketua": "Yuhana",
        "Nama Sekretaris": "Amin",
        "Nama Bendahara": "Wakkar",
        "Nama Pengawas": " ",
        "Nama Manager": " ",
        "Jumlah Anggota Pria": "27",
        "Jumlah Anggota Wanita": "7",
        "Total Anggota": "34",
        "Total Manajer": "2",
        "Total Karyawan": "1",
        "Nomor Induk Koperasi (NIK)": "7316020010006",
        "Status NIK": "Belum Bersertifikat",
        "Tanggal Berlaku Sertifikat": " ",
        "Status Grade": "D"
    },
    "7316020010007": {
        "Koperasi": "Koperasi Uni Usaha Pondok Pesantren Darul Falah Enrekang",
        "Nomor Badan Hukum Pendirian": "3877/BH/IV",
        "Tanggal Badan Hukum Pendirian": "26/08/1975",
        "Nomor Perubahan Anggaran Dasar (Terbaru)": " ",
        "Tanggal Perubahan Anggaran Dasar (Terbaru)": " ",
        "Tanggal RAT Terakhir": " ",
        "Alamat": "Jl. Jenderal Sudirman Enrekang",
        "Kelurahan / Desa": "Kelurahan Galonta",
        "Kecamatan": "Enrekang",
        "Kabupaten": "Kab. Enrekang",
        "Provinsi": "Sulawesi Selatan",
        "Bentuk Koperasi": "Primer Kabupaten/Kota",
        "Jenis Koperasi": "Konsumen",
        "Kelompok Koperasi": "Koppontren",
        "Sektor Usaha": "Jasa Keuangan dan Asuransi",
        "Nama Ketua": " ",
        "Nama Sekretaris": " ",
        "Nama Bendahara": " ",
        "Nama Pengawas": " ",
        "Nama Manager": " ",
        "Jumlah Anggota Pria": "0",
        "Jumlah Anggota Wanita": "0",
        "Total Anggota": "0",
        "Total Manajer": "0",
        "Total Karyawan": "0",
        "Nomor Induk Koperasi (NIK)": "7316020010007",
        "Status NIK": "Belum Bersertifikat",
        "Tanggal Berlaku Sertifikat": " ",
        "Status Grade": "D"
    },
    "7316020010017": {
        "Koperasi": "Koperasi Pegawai Negeri Sekolah Menengah Pertama Negeri 2 Enrekang",
        "Nomor Badan Hukum Pendirian": "4429/BH/IV",
        "Tanggal Badan Hukum Pendirian": "29/03/1985",
        "Nomor Perubahan Anggaran Dasar (Terbaru)": " ",
        "Tanggal Perubahan Anggaran Dasar (Terbaru)": " ",
        "Tanggal RAT Terakhir": " ",
        "Alamat": "Jl. Emmy Saelan Enrekang",
        "Kelurahan / Desa": "Kelurahan Juppandang",
        "Kecamatan": "Enrekang",
        "Kabupaten": "Kab. Enrekang",
        "Provinsi": "Sulawesi Selatan",
        "Bentuk Koperasi": "Primer Kabupaten/Kota",
        "Jenis Koperasi": "Konsumen",
        "Kelompok Koperasi": "Kop. Pegawai Negeri (KPRI)",
        "Sektor Usaha": "Jasa Lainnya",
        "Nama Ketua": " ",
        "Nama Sekretaris": " ",
        "Nama Bendahara": " ",
        "Nama Pengawas": " ",
        "Nama Manager": " ",
        "Jumlah Anggota Pria": "0",
        "Jumlah Anggota Wanita": "0",
        "Total Anggota": "0",
        "Total Manajer": "0",
        "Total Karyawan": "0",
        "Nomor Induk Koperasi (NIK)": "7316020010017",
        "Status NIK": "Belum Bersertifikat",
        "Tanggal Berlaku Sertifikat": " ",
        "Status Grade": "D"
    },
    "7316020010029": {
        "Koperasi": "Koperasi Pegawai Negeri Tanggap",
        "Nomor Badan Hukum Pendirian": "5281/BH/IV",
        "Tanggal Badan Hukum Pendirian": "17/07/1992",
        "Nomor Perubahan Anggaran Dasar (Terbaru)": " ",
        "Tanggal Perubahan Anggaran Dasar (Terbaru)": " ",
        "Tanggal RAT Terakhir": " ",
        "Alamat": "Jl. Sultan hasanuddin Enrekang",
        "Kelurahan / Desa": "Kelurahan Juppandang",
        "Kecamatan": "Enrekang",
        "Kabupaten": "Kab. Enrekang",
        "Provinsi": "Sulawesi Selatan",
        "Bentuk Koperasi": "Primer Kabupaten/Kota",
        "Jenis Koperasi": "Konsumen",
        "Kelompok Koperasi": "Kop. Pegawai Negeri (KPRI)",
        "Sektor Usaha": "Jasa Keuangan dan Asuransi",
        "Nama Ketua": " ",
        "Nama Sekretaris": " ",
        "Nama Bendahara": " ",
        "Nama Pengawas": " ",
        "Nama Manager": " ",
        "Jumlah Anggota Pria": "0",
        "Jumlah Anggota Wanita": "0",
        "Total Anggota": "0",
        "Total Manajer": "0",
        "Total Karyawan": "0",
        "Nomor Induk Koperasi (NIK)": "7316020010029",
        "Status NIK": "Belum Bersertifikat",
        "Tanggal Berlaku Sertifikat": " ",
        "Status Grade": "D"
    },
    "7316020010035": {
        "Koperasi": "Koperasi Karyawan PDAM Enrekang Tirta Maspul",
        "Nomor Badan Hukum Pendirian": "145/BH/KWK.20/X/1996",
        "Tanggal Badan Hukum Pendirian": "30/11/1996",
        "Nomor Perubahan Anggaran Dasar (Terbaru)": " ",
        "Tanggal Perubahan Anggaran Dasar (Terbaru)": " ",
        "Tanggal RAT Terakhir": "12/07/2021",
        "Alamat": "Jl. Dipenogoro No. 23 Enrekang",
        "Kelurahan / Desa": "Kelurahan Juppandang",
        "Kecamatan": "Enrekang",
        "Kabupaten": "Kab. Enrekang",
        "Provinsi": "Sulawesi Selatan",
        "Bentuk Koperasi": "Primer Kabupaten/Kota",
        "Jenis Koperasi": "Konsumen",
        "Kelompok Koperasi": "Kopkar",
        "Sektor Usaha": "Jasa Keuangan dan Asuransi",
        "Nama Ketua": "Rachmad, S.Sos",
        "Nama Sekretaris": "Hj. Misvayanti, S.Sos",
        "Nama Bendahara": "Dukumia, S.Sos",
        "Nama Pengawas": " ",
        "Nama Manager": " ",
        "Jumlah Anggota Pria": "45",
        "Jumlah Anggota Wanita": "10",
        "Total Anggota": "55",
        "Total Manajer": "0",
        "Total Karyawan": "0",
        "Nomor Induk Koperasi (NIK)": "7316020010035",
        "Status NIK": "Belum Bersertifikat",
        "Tanggal Berlaku Sertifikat": " ",
        "Status Grade": "D"
    }
}